{
  "symbol": "NIFTY 50",
  "expiry": "2026-04-07",
  "date": "2026-04-01",
  "time": "22:38:11",
  "spot": 22679.4,
  "strikes": [
    {
      "strike": 20200,
      "call_oi": 0,
      "put_oi": 9771775,
      "call_prev": 0,
      "put_prev": 3494920,
      "call_ltp": 0,
      "put_ltp": 4.8,
      "call_vol": 0,
      "put_vol": 32485180,
      "call_iv": 0,
      "put_iv": 40.77,
      "call_delta": 1,
      "put_delta": -0.0115
    },
    {
      "strike": 20250,
      "call_oi": 0,
      "put_oi": 718380,
      "call_prev": 0,
      "put_prev": 30875,
      "call_ltp": 0,
      "put_ltp": 4.8,
      "call_vol": 0,
      "put_vol": 5742035,
      "call_iv": 0,
      "put_iv": 40.04,
      "call_delta": 1,
      "put_delta": -0.0117
    },
    {
      "strike": 20300,
      "call_oi": 0,
      "put_oi": 537030,
      "call_prev": 0,
      "put_prev": 201630,
      "call_ltp": 0,
      "put_ltp": 4.95,
      "call_vol": 0,
      "put_vol": 5051280,
      "call_iv": 0,
      "put_iv": 39.43,
      "call_delta": 1,
      "put_delta": -0.0121
    },
    {
      "strike": 20350,
      "call_oi": 0,
      "put_oi": 84370,
      "call_prev": 0,
      "put_prev": 44525,
      "call_ltp": 0,
      "put_ltp": 5.05,
      "call_vol": 0,
      "put_vol": 1390675,
      "call_iv": 0,
      "put_iv": 38.82,
      "call_delta": 1,
      "put_delta": -0.0126
    },
    {
      "strike": 20400,
      "call_oi": 0,
      "put_oi": 320970,
      "call_prev": 0,
      "put_prev": 145015,
      "call_ltp": 0,
      "put_ltp": 5.55,
      "call_vol": 0,
      "put_vol": 4243135,
      "call_iv": 0,
      "put_iv": 38.45,
      "call_delta": 1,
      "put_delta": -0.0136
    },
    {
      "strike": 20450,
      "call_oi": 0,
      "put_oi": 98995,
      "call_prev": 0,
      "put_prev": 24570,
      "call_ltp": 0,
      "put_ltp": 5.6,
      "call_vol": 0,
      "put_vol": 1534065,
      "call_iv": 0,
      "put_iv": 37.84,
      "call_delta": 1,
      "put_delta": -0.0141
    },
    {
      "strike": 20500,
      "call_oi": 40495,
      "put_oi": 4654975,
      "call_prev": 39910,
      "put_prev": 4904900,
      "call_ltp": 2239.9,
      "put_ltp": 5.95,
      "call_vol": 30485,
      "put_vol": 21972730,
      "call_iv": 45.68,
      "put_iv": 37.48,
      "call_delta": 0.9628,
      "put_delta": -0.0152
    },
    {
      "strike": 20550,
      "call_oi": 65,
      "put_oi": 207415,
      "call_prev": 65,
      "put_prev": 93145,
      "call_ltp": 2244.75,
      "put_ltp": 6.35,
      "call_vol": 0,
      "put_vol": 2363595,
      "call_iv": 59.81,
      "put_iv": 37.05,
      "call_delta": 0.9111,
      "put_delta": -0.0163
    },
    {
      "strike": 20600,
      "call_oi": 325,
      "put_oi": 709280,
      "call_prev": 195,
      "put_prev": 946140,
      "call_ltp": 2161.6,
      "put_ltp": 6.75,
      "call_vol": 260,
      "put_vol": 8127795,
      "call_iv": 51.06,
      "put_iv": 36.5,
      "call_delta": 0.9369,
      "put_delta": -0.0172
    },
    {
      "strike": 20650,
      "call_oi": 0,
      "put_oi": 182390,
      "call_prev": 0,
      "put_prev": 4355,
      "call_ltp": 0,
      "put_ltp": 7.1,
      "call_vol": 0,
      "put_vol": 1790880,
      "call_iv": 0,
      "put_iv": 36.07,
      "call_delta": 1,
      "put_delta": -0.0184
    },
    {
      "strike": 20700,
      "call_oi": 65,
      "put_oi": 654485,
      "call_prev": 130,
      "put_prev": 0,
      "call_ltp": 1900,
      "put_ltp": 7.75,
      "call_vol": 0,
      "put_vol": 6721845,
      "call_iv": 0,
      "put_iv": 35.71,
      "call_delta": 1,
      "put_delta": -0.0199
    },
    {
      "strike": 20750,
      "call_oi": 130,
      "put_oi": 205855,
      "call_prev": 130,
      "put_prev": 0,
      "call_ltp": 1679.35,
      "put_ltp": 8.1,
      "call_vol": 0,
      "put_vol": 2791945,
      "call_iv": 0,
      "put_iv": 35.28,
      "call_delta": 1,
      "put_delta": -0.0213
    },
    {
      "strike": 20800,
      "call_oi": 65,
      "put_oi": 898235,
      "call_prev": 130,
      "put_prev": 31525,
      "call_ltp": 1810,
      "put_ltp": 8.7,
      "call_vol": 0,
      "put_vol": 6734455,
      "call_iv": 0,
      "put_iv": 34.73,
      "call_delta": 1,
      "put_delta": -0.0225
    },
    {
      "strike": 20850,
      "call_oi": 65,
      "put_oi": 217945,
      "call_prev": 130,
      "put_prev": 0,
      "call_ltp": 1853.35,
      "put_ltp": 9.5,
      "call_vol": 0,
      "put_vol": 2502110,
      "call_iv": 0,
      "put_iv": 34.42,
      "call_delta": 1,
      "put_delta": -0.0245
    },
    {
      "strike": 20900,
      "call_oi": 195,
      "put_oi": 1004185,
      "call_prev": 260,
      "put_prev": 4615,
      "call_ltp": 1700,
      "put_ltp": 10,
      "call_vol": 0,
      "put_vol": 6823440,
      "call_iv": 0,
      "put_iv": 33.94,
      "call_delta": 1,
      "put_delta": -0.0262
    },
    {
      "strike": 20950,
      "call_oi": 130,
      "put_oi": 155090,
      "call_prev": 130,
      "put_prev": 0,
      "call_ltp": 1659.05,
      "put_ltp": 10.85,
      "call_vol": 0,
      "put_vol": 3473145,
      "call_iv": 0,
      "put_iv": 33.75,
      "call_delta": 1,
      "put_delta": -0.029
    },
    {
      "strike": 21000,
      "call_oi": 693745,
      "put_oi": 5996315,
      "call_prev": 703885,
      "put_prev": 3960645,
      "call_ltp": 1745,
      "put_ltp": 11.8,
      "call_vol": 183235,
      "put_vol": 32637215,
      "call_iv": 38.48,
      "put_iv": 33.26,
      "call_delta": 0.9474,
      "put_delta": -0.031
    },
    {
      "strike": 21050,
      "call_oi": 390,
      "put_oi": 141115,
      "call_prev": 390,
      "put_prev": 0,
      "call_ltp": 1900,
      "put_ltp": 12.8,
      "call_vol": 65,
      "put_vol": 3252990,
      "call_iv": 73.14,
      "put_iv": 33.02,
      "call_delta": 0.8036,
      "put_delta": -0.0341
    },
    {
      "strike": 21100,
      "call_oi": 2015,
      "put_oi": 537485,
      "call_prev": 1820,
      "put_prev": 2860,
      "call_ltp": 1373.9,
      "put_ltp": 13.95,
      "call_vol": 0,
      "put_vol": 7117630,
      "call_iv": 0,
      "put_iv": 32.65,
      "call_delta": 1,
      "put_delta": -0.0369
    },
    {
      "strike": 21150,
      "call_oi": 195,
      "put_oi": 186030,
      "call_prev": 195,
      "put_prev": 0,
      "call_ltp": 1527.1,
      "put_ltp": 15.35,
      "call_vol": 0,
      "put_vol": 3587350,
      "call_iv": 0,
      "put_iv": 32.32,
      "call_delta": 1,
      "put_delta": -0.0402
    },
    {
      "strike": 21200,
      "call_oi": 910,
      "put_oi": 1027585,
      "call_prev": 910,
      "put_prev": 680290,
      "call_ltp": 1731.9,
      "put_ltp": 16.8,
      "call_vol": 455,
      "put_vol": 12251460,
      "call_iv": 65.51,
      "put_iv": 31.98,
      "call_delta": 0.8068,
      "put_delta": -0.0437
    },
    {
      "strike": 21250,
      "call_oi": 65,
      "put_oi": 611650,
      "call_prev": 65,
      "put_prev": 0,
      "call_ltp": 1379.4,
      "put_ltp": 18,
      "call_vol": 0,
      "put_vol": 5986500,
      "call_iv": 0,
      "put_iv": 31.56,
      "call_delta": 1,
      "put_delta": -0.0471
    },
    {
      "strike": 21300,
      "call_oi": 325,
      "put_oi": 902200,
      "call_prev": 325,
      "put_prev": 0,
      "call_ltp": 1460.3,
      "put_ltp": 20.05,
      "call_vol": 195,
      "put_vol": 11336780,
      "call_iv": 36.74,
      "put_iv": 31.28,
      "call_delta": 0.9182,
      "put_delta": -0.0517
    },
    {
      "strike": 21350,
      "call_oi": 585,
      "put_oi": 357695,
      "call_prev": 585,
      "put_prev": 0,
      "call_ltp": 1400,
      "put_ltp": 21.75,
      "call_vol": 195,
      "put_vol": 6819215,
      "call_iv": 31.92,
      "put_iv": 31.04,
      "call_delta": 0.9389,
      "put_delta": -0.0568
    },
    {
      "strike": 21400,
      "call_oi": 845,
      "put_oi": 574275,
      "call_prev": 1235,
      "put_prev": 16445,
      "call_ltp": 1350,
      "put_ltp": 24.4,
      "call_vol": 650,
      "put_vol": 12940200,
      "call_iv": 32.29,
      "put_iv": 30.79,
      "call_delta": 0.9287,
      "put_delta": -0.0623
    },
    {
      "strike": 21450,
      "call_oi": 1365,
      "put_oi": 494910,
      "call_prev": 1430,
      "put_prev": 650,
      "call_ltp": 1375.65,
      "put_ltp": 27,
      "call_vol": 260,
      "put_vol": 7356765,
      "call_iv": 44.36,
      "put_iv": 30.49,
      "call_delta": 0.8515,
      "put_delta": -0.068
    },
    {
      "strike": 21500,
      "call_oi": 217230,
      "put_oi": 3954990,
      "call_prev": 273715,
      "put_prev": 3364855,
      "call_ltp": 1270,
      "put_ltp": 29.85,
      "call_vol": 165555,
      "put_vol": 47059675,
      "call_iv": 34.61,
      "put_iv": 30.18,
      "call_delta": 0.8972,
      "put_delta": -0.0742
    },
    {
      "strike": 21550,
      "call_oi": 780,
      "put_oi": 818090,
      "call_prev": 975,
      "put_prev": 585,
      "call_ltp": 1328.5,
      "put_ltp": 32.55,
      "call_vol": 520,
      "put_vol": 8561085,
      "call_iv": 49.45,
      "put_iv": 29.86,
      "call_delta": 0.8066,
      "put_delta": -0.0808
    },
    {
      "strike": 21600,
      "call_oi": 1495,
      "put_oi": 2075710,
      "call_prev": 910,
      "put_prev": 29510,
      "call_ltp": 1160.2,
      "put_ltp": 35.7,
      "call_vol": 2795,
      "put_vol": 18833490,
      "call_iv": 30.58,
      "put_iv": 29.65,
      "call_delta": 0.9047,
      "put_delta": -0.0887
    },
    {
      "strike": 21650,
      "call_oi": 2470,
      "put_oi": 524290,
      "call_prev": 2145,
      "put_prev": 174460,
      "call_ltp": 1131.7,
      "put_ltp": 39.6,
      "call_vol": 3055,
      "put_vol": 11523200,
      "call_iv": 33.42,
      "put_iv": 29.5,
      "call_delta": 0.8743,
      "put_delta": -0.0978
    },
    {
      "strike": 21700,
      "call_oi": 9620,
      "put_oi": 1323335,
      "call_prev": 7475,
      "put_prev": 413530,
      "call_ltp": 1072.35,
      "put_ltp": 43.95,
      "call_vol": 23075,
      "put_vol": 23121280,
      "call_iv": 30.73,
      "put_iv": 29.14,
      "call_delta": 0.882,
      "put_delta": -0.1061
    },
    {
      "strike": 21750,
      "call_oi": 2925,
      "put_oi": 271375,
      "call_prev": 2990,
      "put_prev": 112190,
      "call_ltp": 1038.9,
      "put_ltp": 49.05,
      "call_vol": 8905,
      "put_vol": 10829195,
      "call_iv": 32.3,
      "put_iv": 29.01,
      "call_delta": 0.8586,
      "put_delta": -0.1167
    },
    {
      "strike": 21800,
      "call_oi": 26585,
      "put_oi": 1060085,
      "call_prev": 30030,
      "put_prev": 739180,
      "call_ltp": 1019.75,
      "put_ltp": 54.15,
      "call_vol": 76310,
      "put_vol": 28463955,
      "call_iv": 31.72,
      "put_iv": 28.88,
      "call_delta": 0.85,
      "put_delta": -0.1283
    },
    {
      "strike": 21850,
      "call_oi": 3835,
      "put_oi": 280345,
      "call_prev": 5655,
      "put_prev": 84825,
      "call_ltp": 935.4,
      "put_ltp": 59.4,
      "call_vol": 14040,
      "put_vol": 11826620,
      "call_iv": 29.45,
      "put_iv": 28.66,
      "call_delta": 0.8537,
      "put_delta": -0.1399
    },
    {
      "strike": 21900,
      "call_oi": 23725,
      "put_oi": 716560,
      "call_prev": 15860,
      "put_prev": 279435,
      "call_ltp": 901.85,
      "put_ltp": 66.25,
      "call_vol": 70330,
      "put_vol": 20631000,
      "call_iv": 30.59,
      "put_iv": 28.43,
      "call_delta": 0.8306,
      "put_delta": -0.1523
    },
    {
      "strike": 21950,
      "call_oi": 5980,
      "put_oi": 253435,
      "call_prev": 12610,
      "put_prev": 6955,
      "call_ltp": 854.9,
      "put_ltp": 72.75,
      "call_vol": 15925,
      "put_vol": 11740040,
      "call_iv": 29.78,
      "put_iv": 28.15,
      "call_delta": 0.8217,
      "put_delta": -0.1653
    },
    {
      "strike": 22000,
      "call_oi": 387790,
      "put_oi": 3595280,
      "call_prev": 442780,
      "put_prev": 2595580,
      "call_ltp": 832.65,
      "put_ltp": 80.1,
      "call_vol": 1096225,
      "put_vol": 72908095,
      "call_iv": 31.82,
      "put_iv": 28.08,
      "call_delta": 0.7909,
      "put_delta": -0.1808
    },
    {
      "strike": 22050,
      "call_oi": 14885,
      "put_oi": 261690,
      "call_prev": 16250,
      "put_prev": 67015,
      "call_ltp": 778.85,
      "put_ltp": 88.1,
      "call_vol": 57200,
      "put_vol": 14019460,
      "call_iv": 30.18,
      "put_iv": 27.73,
      "call_delta": 0.786,
      "put_delta": -0.195
    },
    {
      "strike": 22100,
      "call_oi": 57135,
      "put_oi": 892970,
      "call_prev": 49920,
      "put_prev": 391950,
      "call_ltp": 739.55,
      "put_ltp": 97.8,
      "call_vol": 196560,
      "put_vol": 25652900,
      "call_iv": 30.08,
      "put_iv": 27.68,
      "call_delta": 0.7693,
      "put_delta": -0.2127
    },
    {
      "strike": 22150,
      "call_oi": 27300,
      "put_oi": 247910,
      "call_prev": 25805,
      "put_prev": 108875,
      "call_ltp": 695.75,
      "put_ltp": 107.1,
      "call_vol": 130000,
      "put_vol": 14457625,
      "call_iv": 29.37,
      "put_iv": 27.48,
      "call_delta": 0.7559,
      "put_delta": -0.2301
    },
    {
      "strike": 22200,
      "call_oi": 186095,
      "put_oi": 1231295,
      "call_prev": 163085,
      "put_prev": 461955,
      "call_ltp": 679.35,
      "put_ltp": 116.8,
      "call_vol": 552305,
      "put_vol": 34794890,
      "call_iv": 30.41,
      "put_iv": 27.13,
      "call_delta": 0.7301,
      "put_delta": -0.2474
    },
    {
      "strike": 22250,
      "call_oi": 42380,
      "put_oi": 284505,
      "call_prev": 77610,
      "put_prev": 149955,
      "call_ltp": 625,
      "put_ltp": 129.35,
      "call_vol": 276900,
      "put_vol": 14169090,
      "call_iv": 29.54,
      "put_iv": 26.99,
      "call_delta": 0.7158,
      "put_delta": -0.2673
    },
    {
      "strike": 22300,
      "call_oi": 324285,
      "put_oi": 1126645,
      "call_prev": 576160,
      "put_prev": 1082770,
      "call_ltp": 600,
      "put_ltp": 141.65,
      "call_vol": 1922115,
      "put_vol": 30338360,
      "call_iv": 29.53,
      "put_iv": 26.7,
      "call_delta": 0.6955,
      "put_delta": -0.2871
    },
    {
      "strike": 22350,
      "call_oi": 407030,
      "put_oi": 356655,
      "call_prev": 560885,
      "put_prev": 326040,
      "call_ltp": 560.9,
      "put_ltp": 153.35,
      "call_vol": 990665,
      "put_vol": 16558490,
      "call_iv": 29.82,
      "put_iv": 26.69,
      "call_delta": 0.673,
      "put_delta": -0.3097
    },
    {
      "strike": 22400,
      "call_oi": 394485,
      "put_oi": 1342510,
      "call_prev": 832910,
      "put_prev": 980525,
      "call_ltp": 524.25,
      "put_ltp": 167.65,
      "call_vol": 2454465,
      "put_vol": 33940270,
      "call_iv": 29.3,
      "put_iv": 26.31,
      "call_delta": 0.654,
      "put_delta": -0.3311
    },
    {
      "strike": 22450,
      "call_oi": 120770,
      "put_oi": 457210,
      "call_prev": 218725,
      "put_prev": 220025,
      "call_ltp": 487.75,
      "put_ltp": 183.45,
      "call_vol": 1154790,
      "put_vol": 16546790,
      "call_iv": 29.07,
      "put_iv": 26.21,
      "call_delta": 0.6327,
      "put_delta": -0.3549
    },
    {
      "strike": 22500,
      "call_oi": 1592500,
      "put_oi": 2931760,
      "call_prev": 2386865,
      "put_prev": 2459405,
      "call_ltp": 457.75,
      "put_ltp": 200.4,
      "call_vol": 11242530,
      "put_vol": 69646850,
      "call_iv": 28.77,
      "put_iv": 26.07,
      "call_delta": 0.611,
      "put_delta": -0.3793
    },
    {
      "strike": 22550,
      "call_oi": 159120,
      "put_oi": 461500,
      "call_prev": 223145,
      "put_prev": 140270,
      "call_ltp": 424.4,
      "put_ltp": 217.75,
      "call_vol": 2384915,
      "put_vol": 20059325,
      "call_iv": 28.59,
      "put_iv": 25.82,
      "call_delta": 0.5882,
      "put_delta": -0.404
    },
    {
      "strike": 22600,
      "call_oi": 835965,
      "put_oi": 1188980,
      "call_prev": 1118390,
      "put_prev": 728845,
      "call_ltp": 392.4,
      "put_ltp": 235.25,
      "call_vol": 11845340,
      "put_vol": 45911580,
      "call_iv": 28.2,
      "put_iv": 25.61,
      "call_delta": 0.5652,
      "put_delta": -0.4296
    },
    {
      "strike": 22650,
      "call_oi": 578370,
      "put_oi": 997620,
      "call_prev": 183885,
      "put_prev": 90740,
      "call_ltp": 362.3,
      "put_ltp": 255.75,
      "call_vol": 11314810,
      "put_vol": 31790980,
      "call_iv": 28.11,
      "put_iv": 25.35,
      "call_delta": 0.5411,
      "put_delta": -0.4559
    },
    {
      "strike": 22700,
      "call_oi": 2305550,
      "put_oi": 2304250,
      "call_prev": 787345,
      "put_prev": 390975,
      "call_ltp": 333.35,
      "put_ltp": 276,
      "call_vol": 40396005,
      "put_vol": 71966895,
      "call_iv": 27.71,
      "put_iv": 25.11,
      "call_delta": 0.5168,
      "put_delta": -0.4828
    },
    {
      "strike": 22750,
      "call_oi": 717730,
      "put_oi": 649025,
      "call_prev": 141115,
      "put_prev": 39910,
      "call_ltp": 306.05,
      "put_ltp": 299.65,
      "call_vol": 30806815,
      "put_vol": 47520720,
      "call_iv": 27.48,
      "put_iv": 24.6,
      "call_delta": 0.4919,
      "put_delta": -0.5106
    },
    {
      "strike": 22800,
      "call_oi": 2240680,
      "put_oi": 1445730,
      "call_prev": 1112150,
      "put_prev": 478725,
      "call_ltp": 279.65,
      "put_ltp": 321.95,
      "call_vol": 91159835,
      "put_vol": 103725700,
      "call_iv": 27.34,
      "put_iv": 24.44,
      "call_delta": 0.4669,
      "put_delta": -0.5386
    },
    {
      "strike": 22850,
      "call_oi": 958815,
      "put_oi": 605670,
      "call_prev": 180505,
      "put_prev": 70850,
      "call_ltp": 255.95,
      "put_ltp": 348.3,
      "call_vol": 56490655,
      "put_vol": 51517830,
      "call_iv": 27.03,
      "put_iv": 24.36,
      "call_delta": 0.4413,
      "put_delta": -0.5665
    },
    {
      "strike": 22900,
      "call_oi": 2254980,
      "put_oi": 1300000,
      "call_prev": 695045,
      "put_prev": 335790,
      "call_ltp": 233.5,
      "put_ltp": 373.55,
      "call_vol": 99566805,
      "put_vol": 72857785,
      "call_iv": 26.95,
      "put_iv": 24.06,
      "call_delta": 0.4162,
      "put_delta": -0.5951
    },
    {
      "strike": 22950,
      "call_oi": 781170,
      "put_oi": 453115,
      "call_prev": 200915,
      "put_prev": 75660,
      "call_ltp": 211.1,
      "put_ltp": 401.25,
      "call_vol": 33250425,
      "put_vol": 17271540,
      "call_iv": 26.66,
      "put_iv": 23.8,
      "call_delta": 0.3905,
      "put_delta": -0.6237
    },
    {
      "strike": 23000,
      "call_oi": 4633590,
      "put_oi": 2049060,
      "call_prev": 2818140,
      "put_prev": 1350700,
      "call_ltp": 190,
      "put_ltp": 431.35,
      "call_vol": 107500120,
      "put_vol": 36185110,
      "call_iv": 26.47,
      "put_iv": 23.45,
      "call_delta": 0.3653,
      "put_delta": -0.6527
    },
    {
      "strike": 23050,
      "call_oi": 551655,
      "put_oi": 156325,
      "call_prev": 302315,
      "put_prev": 139165,
      "call_ltp": 171.15,
      "put_ltp": 462.85,
      "call_vol": 20405515,
      "put_vol": 3284775,
      "call_iv": 26.31,
      "put_iv": 23.32,
      "call_delta": 0.3405,
      "put_delta": -0.6801
    },
    {
      "strike": 23100,
      "call_oi": 1687920,
      "put_oi": 468845,
      "call_prev": 1146340,
      "put_prev": 414635,
      "call_ltp": 154.2,
      "put_ltp": 495.35,
      "call_vol": 37331580,
      "put_vol": 5711615,
      "call_iv": 26.32,
      "put_iv": 23.09,
      "call_delta": 0.3174,
      "put_delta": -0.7075
    },
    {
      "strike": 23150,
      "call_oi": 585390,
      "put_oi": 85085,
      "call_prev": 209040,
      "put_prev": 54405,
      "call_ltp": 138.75,
      "put_ltp": 526.55,
      "call_vol": 18845125,
      "put_vol": 1082055,
      "call_iv": 26.16,
      "put_iv": 22.77,
      "call_delta": 0.2937,
      "put_delta": -0.7351
    },
    {
      "strike": 23200,
      "call_oi": 2815670,
      "put_oi": 440505,
      "call_prev": 2240875,
      "put_prev": 548015,
      "call_ltp": 123.6,
      "put_ltp": 564.9,
      "call_vol": 56371835,
      "put_vol": 3195985,
      "call_iv": 26.02,
      "put_iv": 22.23,
      "call_delta": 0.2708,
      "put_delta": -0.7641
    },
    {
      "strike": 23250,
      "call_oi": 643175,
      "put_oi": 58825,
      "call_prev": 300495,
      "put_prev": 124735,
      "call_ltp": 110.25,
      "put_ltp": 617.7,
      "call_vol": 19220695,
      "put_vol": 542490,
      "call_iv": 25.96,
      "put_iv": 23.39,
      "call_delta": 0.2493,
      "put_delta": -0.7747
    },
    {
      "strike": 23300,
      "call_oi": 1985490,
      "put_oi": 235950,
      "call_prev": 1056510,
      "put_prev": 227370,
      "call_ltp": 97.95,
      "put_ltp": 640,
      "call_vol": 40326715,
      "put_vol": 1102335,
      "call_iv": 25.88,
      "put_iv": 22.51,
      "call_delta": 0.2286,
      "put_delta": -0.805
    },
    {
      "strike": 23350,
      "call_oi": 649155,
      "put_oi": 29120,
      "call_prev": 173550,
      "put_prev": 22100,
      "call_ltp": 87.1,
      "put_ltp": 694.15,
      "call_vol": 17290585,
      "put_vol": 106340,
      "call_iv": 25.77,
      "put_iv": 22.87,
      "call_delta": 0.2085,
      "put_delta": -0.8208
    },
    {
      "strike": 23400,
      "call_oi": 1968005,
      "put_oi": 172575,
      "call_prev": 1104025,
      "put_prev": 180375,
      "call_ltp": 77.75,
      "put_ltp": 722,
      "call_vol": 37826880,
      "put_vol": 693680,
      "call_iv": 25.72,
      "put_iv": 21.16,
      "call_delta": 0.1899,
      "put_delta": -0.8585
    },
    {
      "strike": 23450,
      "call_oi": 556010,
      "put_oi": 30095,
      "call_prev": 274040,
      "put_prev": 24050,
      "call_ltp": 68.7,
      "put_ltp": 784.45,
      "call_vol": 16572725,
      "put_vol": 60970,
      "call_iv": 25.71,
      "put_iv": 23.73,
      "call_delta": 0.1728,
      "put_delta": -0.8473
    },
    {
      "strike": 23500,
      "call_oi": 5465005,
      "put_oi": 765245,
      "call_prev": 3533465,
      "put_prev": 618280,
      "call_ltp": 60.6,
      "put_ltp": 807.05,
      "call_vol": 87539205,
      "put_vol": 1711970,
      "call_iv": 25.74,
      "put_iv": 18.95,
      "call_delta": 0.1571,
      "put_delta": -0.9158
    },
    {
      "strike": 23550,
      "call_oi": 495105,
      "put_oi": 44005,
      "call_prev": 290940,
      "put_prev": 45825,
      "call_ltp": 53.45,
      "put_ltp": 865.8,
      "call_vol": 14794845,
      "put_vol": 59150,
      "call_iv": 25.77,
      "put_iv": 22.75,
      "call_delta": 0.1424,
      "put_delta": -0.888
    },
    {
      "strike": 23600,
      "call_oi": 1959685,
      "put_oi": 540215,
      "call_prev": 1235455,
      "put_prev": 510705,
      "call_ltp": 46.8,
      "put_ltp": 904,
      "call_vol": 27112410,
      "put_vol": 294710,
      "call_iv": 25.79,
      "put_iv": 21.33,
      "call_delta": 0.1286,
      "put_delta": -0.9156
    },
    {
      "strike": 23650,
      "call_oi": 454025,
      "put_oi": 10660,
      "call_prev": 135655,
      "put_prev": 8255,
      "call_ltp": 41.4,
      "put_ltp": 961.05,
      "call_vol": 12699895,
      "put_vol": 33345,
      "call_iv": 25.77,
      "put_iv": 23.71,
      "call_delta": 0.1155,
      "put_delta": -0.904
    },
    {
      "strike": 23700,
      "call_oi": 2081560,
      "put_oi": 95745,
      "call_prev": 1104025,
      "put_prev": 85215,
      "call_ltp": 36.5,
      "put_ltp": 990,
      "call_vol": 27268475,
      "put_vol": 117715,
      "call_iv": 25.85,
      "put_iv": 19.07,
      "call_delta": 0.1042,
      "put_delta": -0.9568
    },
    {
      "strike": 23750,
      "call_oi": 699855,
      "put_oi": 14755,
      "call_prev": 185835,
      "put_prev": 14495,
      "call_ltp": 32.2,
      "put_ltp": 1052.6,
      "call_vol": 10579725,
      "put_vol": 22880,
      "call_iv": 25.89,
      "put_iv": 23.62,
      "call_delta": 0.0935,
      "put_delta": -0.9264
    },
    {
      "strike": 23800,
      "call_oi": 2370095,
      "put_oi": 209820,
      "call_prev": 1470885,
      "put_prev": 231465,
      "call_ltp": 28.5,
      "put_ltp": 1083,
      "call_vol": 30128280,
      "put_vol": 196625,
      "call_iv": 26,
      "put_iv": 16.72,
      "call_delta": 0.0843,
      "put_delta": -0.9844
    },
    {
      "strike": 23850,
      "call_oi": 684645,
      "put_oi": 11635,
      "call_prev": 198055,
      "put_prev": 11635,
      "call_ltp": 24.45,
      "put_ltp": 1131.95,
      "call_vol": 10979150,
      "put_vol": 14820,
      "call_iv": 26.02,
      "put_iv": 16.24,
      "call_delta": 0.0751,
      "put_delta": -0.9899
    },
    {
      "strike": 23900,
      "call_oi": 2234180,
      "put_oi": 329680,
      "call_prev": 984750,
      "put_prev": 350740,
      "call_ltp": 21.55,
      "put_ltp": 1182.9,
      "call_vol": 19038500,
      "put_vol": 118495,
      "call_iv": 26.03,
      "put_iv": 17.94,
      "call_delta": 0.0667,
      "put_delta": -0.9857
    },
    {
      "strike": 23950,
      "call_oi": 454870,
      "put_oi": 3575,
      "call_prev": 114335,
      "put_prev": 1820,
      "call_ltp": 19.15,
      "put_ltp": 1270.1,
      "call_vol": 8591570,
      "put_vol": 5785,
      "call_iv": 26.15,
      "put_iv": 30.99,
      "call_delta": 0.0599,
      "put_delta": -0.9045
    },
    {
      "strike": 24000,
      "call_oi": 6273670,
      "put_oi": 743210,
      "call_prev": 3880695,
      "put_prev": 786305,
      "call_ltp": 16.85,
      "put_ltp": 1256.65,
      "call_vol": 58147245,
      "put_vol": 275340,
      "call_iv": 26.12,
      "put_iv": 0,
      "call_delta": 0.0526,
      "put_delta": -1
    },
    {
      "strike": 24050,
      "call_oi": 521560,
      "put_oi": 2340,
      "call_prev": 206765,
      "put_prev": 2340,
      "call_ltp": 15.05,
      "put_ltp": 1360.5,
      "call_vol": 7877025,
      "put_vol": 325,
      "call_iv": 26.37,
      "put_iv": 30.64,
      "call_delta": 0.0478,
      "put_delta": -0.9235
    },
    {
      "strike": 24100,
      "call_oi": 2954575,
      "put_oi": 354705,
      "call_prev": 1395485,
      "put_prev": 354705,
      "call_ltp": 13.05,
      "put_ltp": 1380.1,
      "call_vol": 17926415,
      "put_vol": 7150,
      "call_iv": 26.55,
      "put_iv": 0,
      "call_delta": 0.0431,
      "put_delta": -1
    },
    {
      "strike": 24150,
      "call_oi": 578175,
      "put_oi": 1040,
      "call_prev": 104455,
      "put_prev": 910,
      "call_ltp": 11.8,
      "put_ltp": 1690.3,
      "call_vol": 6650670,
      "put_vol": 0,
      "call_iv": 26.64,
      "put_iv": 65.03,
      "call_delta": 0.0383,
      "put_delta": -0.7542
    },
    {
      "strike": 24200,
      "call_oi": 2661295,
      "put_oi": 556270,
      "call_prev": 1774695,
      "put_prev": 562510,
      "call_ltp": 10.1,
      "put_ltp": 1463.3,
      "call_vol": 18184335,
      "put_vol": 15210,
      "call_iv": 26.76,
      "put_iv": 0,
      "call_delta": 0.0342,
      "put_delta": -1
    },
    {
      "strike": 24250,
      "call_oi": 553410,
      "put_oi": 101855,
      "call_prev": 307450,
      "put_prev": 101985,
      "call_ltp": 9.1,
      "put_ltp": 1846.45,
      "call_vol": 6157125,
      "put_vol": 0,
      "call_iv": 26.89,
      "put_iv": 73.39,
      "call_delta": 0.0305,
      "put_delta": -0.7401
    },
    {
      "strike": 24300,
      "call_oi": 1780155,
      "put_oi": 215670,
      "call_prev": 952705,
      "put_prev": 215995,
      "call_ltp": 7.9,
      "put_ltp": 1579.75,
      "call_vol": 12952290,
      "put_vol": 520,
      "call_iv": 27.04,
      "put_iv": 0,
      "call_delta": 0.0273,
      "put_delta": -1
    },
    {
      "strike": 24350,
      "call_oi": 577525,
      "put_oi": 780,
      "call_prev": 133575,
      "put_prev": 1625,
      "call_ltp": 6.8,
      "put_ltp": 1850,
      "call_vol": 5665530,
      "put_vol": 0,
      "call_iv": 27.1,
      "put_iv": 65.35,
      "call_delta": 0.024,
      "put_delta": -0.7826
    },
    {
      "strike": 24400,
      "call_oi": 1367535,
      "put_oi": 297895,
      "call_prev": 602615,
      "put_prev": 300300,
      "call_ltp": 6.15,
      "put_ltp": 1661.9,
      "call_vol": 10282935,
      "put_vol": 50050,
      "call_iv": 27.22,
      "put_iv": 0,
      "call_delta": 0.0213,
      "put_delta": -1
    },
    {
      "strike": 24450,
      "call_oi": 555620,
      "put_oi": 106470,
      "call_prev": 208000,
      "put_prev": 106470,
      "call_ltp": 5.4,
      "put_ltp": 1558.95,
      "call_vol": 5083390,
      "put_vol": 130,
      "call_iv": 27.4,
      "put_iv": 0,
      "call_delta": 0.0192,
      "put_delta": -1
    },
    {
      "strike": 24500,
      "call_oi": 5920915,
      "put_oi": 947570,
      "call_prev": 3644680,
      "put_prev": 951535,
      "call_ltp": 4.65,
      "put_ltp": 1762.95,
      "call_vol": 28316535,
      "put_vol": 36985,
      "call_iv": 27.34,
      "put_iv": 0,
      "call_delta": 0.0164,
      "put_delta": -1
    },
    {
      "strike": 24550,
      "call_oi": 1135485,
      "put_oi": 1401075,
      "call_prev": 910195,
      "put_prev": 1401140,
      "call_ltp": 4.1,
      "put_ltp": 1650.85,
      "call_vol": 5209945,
      "put_vol": 195,
      "call_iv": 27.65,
      "put_iv": 0,
      "call_delta": 0.0151,
      "put_delta": -1
    },
    {
      "strike": 24600,
      "call_oi": 2225535,
      "put_oi": 852800,
      "call_prev": 1393665,
      "put_prev": 852930,
      "call_ltp": 3.5,
      "put_ltp": 1859.95,
      "call_vol": 11555635,
      "put_vol": 1690,
      "call_iv": 27.53,
      "put_iv": 0,
      "call_delta": 0.0127,
      "put_delta": -1
    },
    {
      "strike": 24650,
      "call_oi": 712790,
      "put_oi": 1639040,
      "call_prev": 81445,
      "put_prev": 1639300,
      "call_ltp": 3.2,
      "put_ltp": 1943,
      "call_vol": 4650555,
      "put_vol": 455,
      "call_iv": 27.95,
      "put_iv": 34.18,
      "call_delta": 0.012,
      "put_delta": -0.967
    },
    {
      "strike": 24700,
      "call_oi": 2375425,
      "put_oi": 1170065,
      "call_prev": 1515215,
      "put_prev": 1170065,
      "call_ltp": 2.7,
      "put_ltp": 1840,
      "call_vol": 13066690,
      "put_vol": 260,
      "call_iv": 27.95,
      "put_iv": 0,
      "call_delta": 0.0103,
      "put_delta": -1
    },
    {
      "strike": 24750,
      "call_oi": 1225250,
      "put_oi": 585130,
      "call_prev": 757835,
      "put_prev": 585065,
      "call_ltp": 2.45,
      "put_ltp": 2374.4,
      "call_vol": 5113810,
      "put_vol": 0,
      "call_iv": 28.08,
      "put_iv": 87.86,
      "call_delta": 0.0091,
      "put_delta": -0.7591
    },
    {
      "strike": 24800,
      "call_oi": 1544400,
      "put_oi": 143130,
      "call_prev": 746655,
      "put_prev": 143585,
      "call_ltp": 2.35,
      "put_ltp": 2061,
      "call_vol": 11656190,
      "put_vol": 3510,
      "call_iv": 28.56,
      "put_iv": 0,
      "call_delta": 0.0088,
      "put_delta": -1
    },
    {
      "strike": 24850,
      "call_oi": 620815,
      "put_oi": 910,
      "call_prev": 510965,
      "put_prev": 845,
      "call_ltp": 2.25,
      "put_ltp": 2230,
      "call_vol": 4707755,
      "put_vol": 0,
      "call_iv": 28.81,
      "put_iv": 59.07,
      "call_delta": 0.008,
      "put_delta": -0.8734
    },
    {
      "strike": 24900,
      "call_oi": 672815,
      "put_oi": 16380,
      "call_prev": 380575,
      "put_prev": 16250,
      "call_ltp": 2.05,
      "put_ltp": 2198.35,
      "call_vol": 6850415,
      "put_vol": 9685,
      "call_iv": 29.05,
      "put_iv": 40.04,
      "call_delta": 0.0073,
      "put_delta": -0.9607
    },
    {
      "strike": 24950,
      "call_oi": 153530,
      "put_oi": 1300,
      "call_prev": 36270,
      "put_prev": 1300,
      "call_ltp": 1.95,
      "put_ltp": 2203.15,
      "call_vol": 2282995,
      "put_vol": 65,
      "call_iv": 29.54,
      "put_iv": 0,
      "call_delta": 0.0071,
      "put_delta": -1
    },
    {
      "strike": 25000,
      "call_oi": 3799640,
      "put_oi": 501995,
      "call_prev": 3109860,
      "put_prev": 511290,
      "call_ltp": 1.8,
      "put_ltp": 2250.6,
      "call_vol": 26123045,
      "put_vol": 122265,
      "call_iv": 29.79,
      "put_iv": 0,
      "call_delta": 0.0065,
      "put_delta": -1
    },
    {
      "strike": 25050,
      "call_oi": 146770,
      "put_oi": 325,
      "call_prev": 45955,
      "put_prev": 455,
      "call_ltp": 1.65,
      "put_ltp": 2160,
      "call_vol": 2582580,
      "put_vol": 455,
      "call_iv": 30.03,
      "put_iv": 0,
      "call_delta": 0.0059,
      "put_delta": -1
    },
    {
      "strike": 25100,
      "call_oi": 220870,
      "put_oi": 2405,
      "call_prev": 204165,
      "put_prev": 2405,
      "call_ltp": 1.6,
      "put_ltp": 2339.2,
      "call_vol": 3934970,
      "put_vol": 715,
      "call_iv": 30.52,
      "put_iv": 0,
      "call_delta": 0.0058,
      "put_delta": -1
    },
    {
      "strike": 25150,
      "call_oi": 88920,
      "put_oi": 195,
      "call_prev": 30810,
      "put_prev": 130,
      "call_ltp": 1.4,
      "put_ltp": 2300,
      "call_vol": 1239030,
      "put_vol": 130,
      "call_iv": 30.52,
      "put_iv": 0,
      "call_delta": 0.005,
      "put_delta": -1
    },
    {
      "strike": 25200,
      "call_oi": 399815,
      "put_oi": 15145,
      "call_prev": 302055,
      "put_prev": 15210,
      "call_ltp": 1.35,
      "put_ltp": 2425.05,
      "call_vol": 5293665,
      "put_vol": 9295,
      "call_iv": 31.01,
      "put_iv": 0,
      "call_delta": 0.0048,
      "put_delta": -1
    },
    {
      "strike": 25250,
      "call_oi": 56745,
      "put_oi": 1495,
      "call_prev": 42055,
      "put_prev": 1495,
      "call_ltp": 1.2,
      "put_ltp": 2473.9,
      "call_vol": 613340,
      "put_vol": 390,
      "call_iv": 31.01,
      "put_iv": 0,
      "call_delta": 0.0042,
      "put_delta": -1
    },
    {
      "strike": 25300,
      "call_oi": 260520,
      "put_oi": 7670,
      "call_prev": 297050,
      "put_prev": 7670,
      "call_ltp": 1.3,
      "put_ltp": 2627.5,
      "call_vol": 5262205,
      "put_vol": 5720,
      "call_iv": 31.98,
      "put_iv": 55.39,
      "call_delta": 0.0046,
      "put_delta": -0.9304
    },
    {
      "strike": 25350,
      "call_oi": 90155,
      "put_oi": 65,
      "call_prev": 25545,
      "put_prev": 65,
      "call_ltp": 1.25,
      "put_ltp": 1392.65,
      "call_vol": 710320,
      "put_vol": 0,
      "call_iv": 31.98,
      "put_iv": 0,
      "call_delta": 0.0041,
      "put_delta": -1
    },
    {
      "strike": 25400,
      "call_oi": 757770,
      "put_oi": 21190,
      "call_prev": 122135,
      "put_prev": 22945,
      "call_ltp": 1.05,
      "put_ltp": 2627.25,
      "call_vol": 5857540,
      "put_vol": 18785,
      "call_iv": 32.23,
      "put_iv": 0,
      "call_delta": 0.0037,
      "put_delta": -1
    },
    {
      "strike": 25450,
      "call_oi": 86320,
      "put_oi": 65,
      "call_prev": 22165,
      "put_prev": 65,
      "call_ltp": 1.05,
      "put_ltp": 2700,
      "call_vol": 1728870,
      "put_vol": 65,
      "call_iv": 32.47,
      "put_iv": 0,
      "call_delta": 0.0035,
      "put_delta": -1
    },
    {
      "strike": 25500,
      "call_oi": 2079155,
      "put_oi": 197665,
      "call_prev": 1791855,
      "put_prev": 215020,
      "call_ltp": 1,
      "put_ltp": 2751.2,
      "call_vol": 16278795,
      "put_vol": 83070,
      "call_iv": 33.2,
      "put_iv": 0,
      "call_delta": 0.0036,
      "put_delta": -1
    },
    {
      "strike": 25550,
      "call_oi": 124410,
      "put_oi": 650,
      "call_prev": 39910,
      "put_prev": 650,
      "call_ltp": 0.95,
      "put_ltp": 2809.7,
      "call_vol": 1253525,
      "put_vol": 65,
      "call_iv": 33.45,
      "put_iv": 0,
      "call_delta": 0.0034,
      "put_delta": -1
    },
    {
      "strike": 25600,
      "call_oi": 294515,
      "put_oi": 6370,
      "call_prev": 275275,
      "put_prev": 6370,
      "call_ltp": 1.05,
      "put_ltp": 2701,
      "call_vol": 3414775,
      "put_vol": 5135,
      "call_iv": 34.18,
      "put_iv": 0,
      "call_delta": 0.0034,
      "put_delta": -1
    },
    {
      "strike": 25650,
      "call_oi": 57070,
      "put_oi": 1040,
      "call_prev": 14560,
      "put_prev": 1040,
      "call_ltp": 0.95,
      "put_ltp": 2872.25,
      "call_vol": 314015,
      "put_vol": 130,
      "call_iv": 34.18,
      "put_iv": 0,
      "call_delta": 0.0031,
      "put_delta": -1
    },
    {
      "strike": 25700,
      "call_oi": 226005,
      "put_oi": 3575,
      "call_prev": 134810,
      "put_prev": 4420,
      "call_ltp": 0.95,
      "put_ltp": 2931,
      "call_vol": 2490670,
      "put_vol": 2925,
      "call_iv": 34.91,
      "put_iv": 0,
      "call_delta": 0.0032,
      "put_delta": -1
    },
    {
      "strike": 25750,
      "call_oi": 45500,
      "put_oi": 390,
      "call_prev": 19630,
      "put_prev": 455,
      "call_ltp": 0.9,
      "put_ltp": 2650,
      "call_vol": 396045,
      "put_vol": 0,
      "call_iv": 35.16,
      "put_iv": 0,
      "call_delta": 0.003,
      "put_delta": -1
    },
    {
      "strike": 25800,
      "call_oi": 168155,
      "put_oi": 6695,
      "call_prev": 128310,
      "put_prev": 5460,
      "call_ltp": 0.9,
      "put_ltp": 3060,
      "call_vol": 2010580,
      "put_vol": 5395,
      "call_iv": 35.64,
      "put_iv": 0,
      "call_delta": 0.0029,
      "put_delta": -1
    },
    {
      "strike": 25850,
      "call_oi": 141440,
      "put_oi": 65,
      "call_prev": 17940,
      "put_prev": 65,
      "call_ltp": 0.9,
      "put_ltp": 1819.75,
      "call_vol": 962975,
      "put_vol": 0,
      "call_iv": 36.13,
      "put_iv": 0,
      "call_delta": 0.0029,
      "put_delta": -1
    },
    {
      "strike": 25900,
      "call_oi": 183755,
      "put_oi": 715,
      "call_prev": 64090,
      "put_prev": 975,
      "call_ltp": 0.85,
      "put_ltp": 2950.25,
      "call_vol": 1654315,
      "put_vol": 325,
      "call_iv": 36.62,
      "put_iv": 0,
      "call_delta": 0.0029,
      "put_delta": -1
    },
    {
      "strike": 25950,
      "call_oi": 72280,
      "put_oi": 65,
      "call_prev": 28990,
      "put_prev": 65,
      "call_ltp": 0.85,
      "put_ltp": 1922.35,
      "call_vol": 603525,
      "put_vol": 0,
      "call_iv": 36.62,
      "put_iv": 0,
      "call_delta": 0.0025,
      "put_delta": -1
    },
    {
      "strike": 26000,
      "call_oi": 1756560,
      "put_oi": 210145,
      "call_prev": 1879345,
      "put_prev": 233545,
      "call_ltp": 0.8,
      "put_ltp": 3243.7,
      "call_vol": 13007735,
      "put_vol": 80015,
      "call_iv": 37.6,
      "put_iv": 0,
      "call_delta": 0.0028,
      "put_delta": -1
    },
    {
      "strike": 26050,
      "call_oi": 49075,
      "put_oi": 65,
      "call_prev": 17680,
      "put_prev": 130,
      "call_ltp": 0.8,
      "put_ltp": 3070,
      "call_vol": 273455,
      "put_vol": 0,
      "call_iv": 37.6,
      "put_iv": 0,
      "call_delta": 0.0025,
      "put_delta": -1
    },
    {
      "strike": 26100,
      "call_oi": 71695,
      "put_oi": 12675,
      "call_prev": 37505,
      "put_prev": 21515,
      "call_ltp": 0.8,
      "put_ltp": 3357.9,
      "call_vol": 529295,
      "put_vol": 19305,
      "call_iv": 38.09,
      "put_iv": 0,
      "call_delta": 0.0024,
      "put_delta": -1
    },
    {
      "strike": 26150,
      "call_oi": 32500,
      "put_oi": 65,
      "call_prev": 9165,
      "put_prev": 65,
      "call_ltp": 0.8,
      "put_ltp": 2146.5,
      "call_vol": 304590,
      "put_vol": 0,
      "call_iv": 38.57,
      "put_iv": 0,
      "call_delta": 0.0024,
      "put_delta": -1
    },
    {
      "strike": 26200,
      "call_oi": 252005,
      "put_oi": 520,
      "call_prev": 186940,
      "put_prev": 650,
      "call_ltp": 0.8,
      "put_ltp": 3780,
      "call_vol": 1006395,
      "put_vol": 0,
      "call_iv": 39.06,
      "put_iv": 112.54,
      "call_delta": 0.0024,
      "put_delta": -0.8201
    },
    {
      "strike": 26250,
      "call_oi": 26390,
      "put_oi": 2600,
      "call_prev": 12155,
      "put_prev": 2600,
      "call_ltp": 0.75,
      "put_ltp": 3512.7,
      "call_vol": 156325,
      "put_vol": 455,
      "call_iv": 39.06,
      "put_iv": 0,
      "call_delta": 0.0022,
      "put_delta": -1
    },
    {
      "strike": 26300,
      "call_oi": 127790,
      "put_oi": 8905,
      "call_prev": 38740,
      "put_prev": 8970,
      "call_ltp": 0.7,
      "put_ltp": 3481.1,
      "call_vol": 769925,
      "put_vol": 5850,
      "call_iv": 39.55,
      "put_iv": 0,
      "call_delta": 0.0022,
      "put_delta": -1
    },
    {
      "strike": 26350,
      "call_oi": 31005,
      "put_oi": 65,
      "call_prev": 15925,
      "put_prev": 65,
      "call_ltp": 0.8,
      "put_ltp": 2349.15,
      "call_vol": 139620,
      "put_vol": 0,
      "call_iv": 40.04,
      "put_iv": 0,
      "call_delta": 0.0021,
      "put_delta": -1
    },
    {
      "strike": 26400,
      "call_oi": 276185,
      "put_oi": 65,
      "call_prev": 141440,
      "put_prev": 65,
      "call_ltp": 0.7,
      "put_ltp": 3530,
      "call_vol": 1190670,
      "put_vol": 0,
      "call_iv": 40.53,
      "put_iv": 0,
      "call_delta": 0.0021,
      "put_delta": -1
    },
    {
      "strike": 26450,
      "call_oi": 21905,
      "put_oi": 65,
      "call_prev": 13195,
      "put_prev": 65,
      "call_ltp": 0.7,
      "put_ltp": 2419.8,
      "call_vol": 146835,
      "put_vol": 0,
      "call_iv": 41.02,
      "put_iv": 0,
      "call_delta": 0.0021,
      "put_delta": -1
    },
    {
      "strike": 26500,
      "call_oi": 1150500,
      "put_oi": 36465,
      "call_prev": 891475,
      "put_prev": 36985,
      "call_ltp": 0.7,
      "put_ltp": 3753.25,
      "call_vol": 3737630,
      "put_vol": 10855,
      "call_iv": 41.5,
      "put_iv": 0,
      "call_delta": 0.0021,
      "put_delta": -1
    },
    {
      "strike": 26550,
      "call_oi": 74620,
      "put_oi": 65,
      "call_prev": 28210,
      "put_prev": 65,
      "call_ltp": 0.75,
      "put_ltp": 2533.15,
      "call_vol": 270985,
      "put_vol": 0,
      "call_iv": 41.99,
      "put_iv": 0,
      "call_delta": 0.0021,
      "put_delta": -1
    },
    {
      "strike": 26600,
      "call_oi": 1029925,
      "put_oi": 2665,
      "call_prev": 818610,
      "put_prev": 2665,
      "call_ltp": 0.7,
      "put_ltp": 3791.3,
      "call_vol": 3255525,
      "put_vol": 1040,
      "call_iv": 41.99,
      "put_iv": 0,
      "call_delta": 0.0019,
      "put_delta": -1
    }
  ]
}