{
  "symbol": "NIFTY50",
  "expiry": "2026-06-09",
  "date": "2026-06-09",
  "time": "09:41:42",
  "spot": 23218,
  "strikes": [
    {
      "strike": 21100,
      "call_oi": 195,
      "put_oi": 2722525,
      "call_prev": 195,
      "put_prev": 5193175,
      "call_ltp": 2180,
      "put_ltp": 0.25,
      "call_vol": 195,
      "put_vol": 7210645,
      "call_iv": 273.44,
      "put_iv": 121.09,
      "call_delta": 0.9183,
      "put_delta": -0.001
    },
    {
      "strike": 21150,
      "call_oi": 0,
      "put_oi": 129285,
      "call_prev": 0,
      "put_prev": 138320,
      "call_ltp": 0,
      "put_ltp": 0.25,
      "call_vol": 0,
      "put_vol": 149500,
      "call_iv": 0,
      "put_iv": 121.09,
      "call_delta": 1,
      "put_delta": -0.0013
    },
    {
      "strike": 21200,
      "call_oi": 0,
      "put_oi": 540800,
      "call_prev": 0,
      "put_prev": 805480,
      "call_ltp": 0,
      "put_ltp": 0.25,
      "call_vol": 0,
      "put_vol": 946725,
      "call_iv": 0,
      "put_iv": 117.19,
      "call_delta": 1,
      "put_delta": -0.0012
    },
    {
      "strike": 21250,
      "call_oi": 65,
      "put_oi": 92040,
      "call_prev": 0,
      "put_prev": 83785,
      "call_ltp": 2073.9,
      "put_ltp": 0.3,
      "call_vol": 130,
      "put_vol": 46150,
      "call_iv": 299.32,
      "put_iv": 113.28,
      "call_delta": 0.8825,
      "put_delta": -0.0011
    },
    {
      "strike": 21300,
      "call_oi": 130,
      "put_oi": 234585,
      "call_prev": 65,
      "put_prev": 430755,
      "call_ltp": 1999,
      "put_ltp": 0.3,
      "call_vol": 0,
      "put_vol": 546715,
      "call_iv": 271.67,
      "put_iv": 113.28,
      "call_delta": 0.8975,
      "put_delta": -0.0015
    },
    {
      "strike": 21350,
      "call_oi": 130,
      "put_oi": 61945,
      "call_prev": 65,
      "put_prev": 59410,
      "call_ltp": 2100.55,
      "put_ltp": 0.3,
      "call_vol": 0,
      "put_vol": 52065,
      "call_iv": 377.99,
      "put_iv": 109.38,
      "call_delta": 0.8187,
      "put_delta": -0.0014
    },
    {
      "strike": 21400,
      "call_oi": 130,
      "put_oi": 260715,
      "call_prev": 65,
      "put_prev": 340665,
      "call_ltp": 1770,
      "put_ltp": 0.3,
      "call_vol": 0,
      "put_vol": 495755,
      "call_iv": 0,
      "put_iv": 109.38,
      "call_delta": 1,
      "put_delta": -0.0018
    },
    {
      "strike": 21450,
      "call_oi": 0,
      "put_oi": 74750,
      "call_prev": 0,
      "put_prev": 77025,
      "call_ltp": 0,
      "put_ltp": 0.35,
      "call_vol": 0,
      "put_vol": 99060,
      "call_iv": 0,
      "put_iv": 105.47,
      "call_delta": 1,
      "put_delta": -0.0017
    },
    {
      "strike": 21500,
      "call_oi": 2340,
      "put_oi": 3005210,
      "call_prev": 2340,
      "put_prev": 3507790,
      "call_ltp": 1735,
      "put_ltp": 0.25,
      "call_vol": 130,
      "put_vol": 4690075,
      "call_iv": 171.63,
      "put_iv": 101.56,
      "call_delta": 0.961,
      "put_delta": -0.0016
    },
    {
      "strike": 21550,
      "call_oi": 130,
      "put_oi": 198250,
      "call_prev": 65,
      "put_prev": 145990,
      "call_ltp": 1651.9,
      "put_ltp": 0.35,
      "call_vol": 0,
      "put_vol": 263445,
      "call_iv": 0,
      "put_iv": 99.61,
      "call_delta": 1,
      "put_delta": -0.0018
    },
    {
      "strike": 21600,
      "call_oi": 0,
      "put_oi": 333060,
      "call_prev": 0,
      "put_prev": 436540,
      "call_ltp": 0,
      "put_ltp": 0.3,
      "call_vol": 0,
      "put_vol": 602615,
      "call_iv": 0,
      "put_iv": 97.66,
      "call_delta": 1,
      "put_delta": -0.002
    },
    {
      "strike": 21650,
      "call_oi": 0,
      "put_oi": 264160,
      "call_prev": 0,
      "put_prev": 234260,
      "call_ltp": 0,
      "put_ltp": 0.4,
      "call_vol": 0,
      "put_vol": 259740,
      "call_iv": 0,
      "put_iv": 95.7,
      "call_delta": 1,
      "put_delta": -0.0022
    },
    {
      "strike": 21700,
      "call_oi": 0,
      "put_oi": 539890,
      "call_prev": 0,
      "put_prev": 619970,
      "call_ltp": 0,
      "put_ltp": 0.4,
      "call_vol": 0,
      "put_vol": 738530,
      "call_iv": 0,
      "put_iv": 93.75,
      "call_delta": 1,
      "put_delta": -0.0024
    },
    {
      "strike": 21750,
      "call_oi": 65,
      "put_oi": 290615,
      "call_prev": 65,
      "put_prev": 121550,
      "call_ltp": 1553.35,
      "put_ltp": 0.35,
      "call_vol": 0,
      "put_vol": 561275,
      "call_iv": 226.07,
      "put_iv": 89.84,
      "call_delta": 0.8751,
      "put_delta": -0.0023
    },
    {
      "strike": 21800,
      "call_oi": 0,
      "put_oi": 1276145,
      "call_prev": 0,
      "put_prev": 1445795,
      "call_ltp": 0,
      "put_ltp": 0.4,
      "call_vol": 0,
      "put_vol": 2353845,
      "call_iv": 0,
      "put_iv": 87.89,
      "call_delta": 1,
      "put_delta": -0.0026
    },
    {
      "strike": 21850,
      "call_oi": 0,
      "put_oi": 188825,
      "call_prev": 0,
      "put_prev": 183040,
      "call_ltp": 0,
      "put_ltp": 0.4,
      "call_vol": 0,
      "put_vol": 361595,
      "call_iv": 0,
      "put_iv": 83.98,
      "call_delta": 1,
      "put_delta": -0.0024
    },
    {
      "strike": 21900,
      "call_oi": 0,
      "put_oi": 809445,
      "call_prev": 0,
      "put_prev": 996710,
      "call_ltp": 0,
      "put_ltp": 0.4,
      "call_vol": 0,
      "put_vol": 1689675,
      "call_iv": 0,
      "put_iv": 82.03,
      "call_delta": 1,
      "put_delta": -0.0028
    },
    {
      "strike": 21950,
      "call_oi": 65,
      "put_oi": 437710,
      "call_prev": 130,
      "put_prev": 230880,
      "call_ltp": 1427,
      "put_ltp": 0.5,
      "call_vol": 0,
      "put_vol": 1072305,
      "call_iv": 253.97,
      "put_iv": 80.08,
      "call_delta": 0.8135,
      "put_delta": -0.0031
    },
    {
      "strike": 22000,
      "call_oi": 17810,
      "put_oi": 6243055,
      "call_prev": 22880,
      "put_prev": 6655740,
      "call_ltp": 1219.55,
      "put_ltp": 0.4,
      "call_vol": 9035,
      "put_vol": 14966185,
      "call_iv": 92.29,
      "put_iv": 76.17,
      "call_delta": 0.9887,
      "put_delta": -0.0029
    },
    {
      "strike": 22050,
      "call_oi": 325,
      "put_oi": 358670,
      "call_prev": 325,
      "put_prev": 268450,
      "call_ltp": 1131.1,
      "put_ltp": 0.5,
      "call_vol": 0,
      "put_vol": 858195,
      "call_iv": 0,
      "put_iv": 74.22,
      "call_delta": 1,
      "put_delta": -0.0034
    },
    {
      "strike": 22100,
      "call_oi": 650,
      "put_oi": 2345070,
      "call_prev": 520,
      "put_prev": 1613430,
      "call_ltp": 1121.65,
      "put_ltp": 0.45,
      "call_vol": 260,
      "put_vol": 6732765,
      "call_iv": 94.24,
      "put_iv": 71.29,
      "call_delta": 0.9796,
      "put_delta": -0.0035
    },
    {
      "strike": 22150,
      "call_oi": 130,
      "put_oi": 649935,
      "call_prev": 130,
      "put_prev": 553670,
      "call_ltp": 1070,
      "put_ltp": 0.5,
      "call_vol": 130,
      "put_vol": 1971710,
      "call_iv": 77.15,
      "put_iv": 68.36,
      "call_delta": 0.9914,
      "put_delta": -0.0036
    },
    {
      "strike": 22200,
      "call_oi": 975,
      "put_oi": 3404115,
      "call_prev": 910,
      "put_prev": 2533700,
      "call_ltp": 917,
      "put_ltp": 0.45,
      "call_vol": 0,
      "put_vol": 8945040,
      "call_iv": 0,
      "put_iv": 65.43,
      "call_delta": 1,
      "put_delta": -0.0038
    },
    {
      "strike": 22250,
      "call_oi": 715,
      "put_oi": 1232530,
      "call_prev": 650,
      "put_prev": 851565,
      "call_ltp": 980.05,
      "put_ltp": 0.5,
      "call_vol": 130,
      "put_vol": 3139955,
      "call_iv": 99.12,
      "put_iv": 62.5,
      "call_delta": 0.9538,
      "put_delta": -0.0039
    },
    {
      "strike": 22300,
      "call_oi": 3705,
      "put_oi": 3531060,
      "call_prev": 3705,
      "put_prev": 3302650,
      "call_ltp": 916,
      "put_ltp": 0.55,
      "call_vol": 1365,
      "put_vol": 9598355,
      "call_iv": 0,
      "put_iv": 60.55,
      "call_delta": 1,
      "put_delta": -0.0047
    },
    {
      "strike": 22350,
      "call_oi": 1300,
      "put_oi": 2220075,
      "call_prev": 1300,
      "put_prev": 2024230,
      "call_ltp": 761.35,
      "put_ltp": 0.55,
      "call_vol": 0,
      "put_vol": 4410835,
      "call_iv": 0,
      "put_iv": 58.59,
      "call_delta": 1,
      "put_delta": -0.0056
    },
    {
      "strike": 22400,
      "call_oi": 9100,
      "put_oi": 5617560,
      "call_prev": 28080,
      "put_prev": 5012540,
      "call_ltp": 854.65,
      "put_ltp": 0.65,
      "call_vol": 26195,
      "put_vol": 11207430,
      "call_iv": 114.2,
      "put_iv": 56.64,
      "call_delta": 0.8917,
      "put_delta": -0.0068
    },
    {
      "strike": 22450,
      "call_oi": 2080,
      "put_oi": 1700465,
      "call_prev": 2730,
      "put_prev": 1570010,
      "call_ltp": 663.9,
      "put_ltp": 0.65,
      "call_vol": 0,
      "put_vol": 5388240,
      "call_iv": 0,
      "put_iv": 52.73,
      "call_delta": 1,
      "put_delta": -0.0064
    },
    {
      "strike": 22500,
      "call_oi": 69550,
      "put_oi": 14552135,
      "call_prev": 66300,
      "put_prev": 10122710,
      "call_ltp": 722.8,
      "put_ltp": 0.7,
      "call_vol": 56030,
      "put_vol": 36297560,
      "call_iv": 64.21,
      "put_iv": 50.29,
      "call_delta": 0.972,
      "put_delta": -0.0074
    },
    {
      "strike": 22550,
      "call_oi": 9100,
      "put_oi": 3000270,
      "call_prev": 8775,
      "put_prev": 1957540,
      "call_ltp": 682.6,
      "put_ltp": 0.75,
      "call_vol": 2405,
      "put_vol": 7950995,
      "call_iv": 78.25,
      "put_iv": 46.88,
      "call_delta": 0.9276,
      "put_delta": -0.0076
    },
    {
      "strike": 22600,
      "call_oi": 24180,
      "put_oi": 5858840,
      "call_prev": 25545,
      "put_prev": 3510390,
      "call_ltp": 623.6,
      "put_ltp": 0.8,
      "call_vol": 16055,
      "put_vol": 18779345,
      "call_iv": 58.35,
      "put_iv": 43.95,
      "call_delta": 0.9645,
      "put_delta": -0.0084
    },
    {
      "strike": 22650,
      "call_oi": 15795,
      "put_oi": 5748340,
      "call_prev": 17095,
      "put_prev": 2554305,
      "call_ltp": 564.95,
      "put_ltp": 0.8,
      "call_vol": 15665,
      "put_vol": 15633865,
      "call_iv": 0,
      "put_iv": 41.02,
      "call_delta": 1,
      "put_delta": -0.0093
    },
    {
      "strike": 22700,
      "call_oi": 44590,
      "put_oi": 9947860,
      "call_prev": 50505,
      "put_prev": 6521125,
      "call_ltp": 527.95,
      "put_ltp": 0.9,
      "call_vol": 43160,
      "put_vol": 29530605,
      "call_iv": 57.37,
      "put_iv": 38.09,
      "call_delta": 0.9378,
      "put_delta": -0.0105
    },
    {
      "strike": 22750,
      "call_oi": 24375,
      "put_oi": 4654910,
      "call_prev": 25480,
      "put_prev": 2742480,
      "call_ltp": 472.6,
      "put_ltp": 1,
      "call_vol": 34905,
      "put_vol": 17672070,
      "call_iv": 44.43,
      "put_iv": 35.64,
      "call_delta": 0.9631,
      "put_delta": -0.013
    },
    {
      "strike": 22800,
      "call_oi": 133640,
      "put_oi": 9705670,
      "call_prev": 139880,
      "put_prev": 6603740,
      "call_ltp": 426.4,
      "put_ltp": 1.15,
      "call_vol": 324285,
      "put_vol": 35821240,
      "call_iv": 48.58,
      "put_iv": 33.2,
      "call_delta": 0.928,
      "put_delta": -0.0165
    },
    {
      "strike": 22850,
      "call_oi": 47060,
      "put_oi": 4777825,
      "call_prev": 53040,
      "put_prev": 2945280,
      "call_ltp": 376,
      "put_ltp": 1.45,
      "call_vol": 136045,
      "put_vol": 32534255,
      "call_iv": 41.63,
      "put_iv": 30.76,
      "call_delta": 0.933,
      "put_delta": -0.0214
    },
    {
      "strike": 22900,
      "call_oi": 285870,
      "put_oi": 9945585,
      "call_prev": 412880,
      "put_prev": 6410495,
      "call_ltp": 328.4,
      "put_ltp": 2.1,
      "call_vol": 1109355,
      "put_vol": 58286475,
      "call_iv": 41.38,
      "put_iv": 28.81,
      "call_delta": 0.9036,
      "put_delta": -0.031
    },
    {
      "strike": 22950,
      "call_oi": 196885,
      "put_oi": 6283615,
      "call_prev": 151125,
      "put_prev": 3338465,
      "call_ltp": 279.1,
      "put_ltp": 3.15,
      "call_vol": 700375,
      "put_vol": 43087655,
      "call_iv": 36.8,
      "put_iv": 26.98,
      "call_delta": 0.8912,
      "put_delta": -0.0466
    },
    {
      "strike": 23000,
      "call_oi": 1654770,
      "put_oi": 21456370,
      "call_prev": 1401985,
      "put_prev": 9927320,
      "call_ltp": 231.35,
      "put_ltp": 5.2,
      "call_vol": 7141290,
      "put_vol": 90139270,
      "call_iv": 31.98,
      "put_iv": 25.76,
      "call_delta": 0.8742,
      "put_delta": -0.0775
    },
    {
      "strike": 23050,
      "call_oi": 1071005,
      "put_oi": 7959250,
      "call_prev": 732615,
      "put_prev": 3642015,
      "call_ltp": 184,
      "put_ltp": 8.6,
      "call_vol": 5950750,
      "put_vol": 51362740,
      "call_iv": 30.03,
      "put_iv": 24.05,
      "call_delta": 0.8281,
      "put_delta": -0.1189
    },
    {
      "strike": 23100,
      "call_oi": 6184490,
      "put_oi": 18888675,
      "call_prev": 4494815,
      "put_prev": 6759090,
      "call_ltp": 140.9,
      "put_ltp": 14.85,
      "call_vol": 30537650,
      "put_vol": 96825625,
      "call_iv": 27.71,
      "put_iv": 22.95,
      "call_delta": 0.7648,
      "put_delta": -0.1921
    },
    {
      "strike": 23150,
      "call_oi": 8201635,
      "put_oi": 15618330,
      "call_prev": 4151875,
      "put_prev": 2910570,
      "call_ltp": 101,
      "put_ltp": 25.15,
      "call_vol": 41586740,
      "put_vol": 83318625,
      "call_iv": 25.73,
      "put_iv": 21.97,
      "call_delta": 0.6738,
      "put_delta": -0.2994
    },
    {
      "strike": 23200,
      "call_oi": 21765900,
      "put_oi": 29011190,
      "call_prev": 8715915,
      "put_prev": 4014660,
      "call_ltp": 67.5,
      "put_ltp": 41.9,
      "call_vol": 115153415,
      "put_vol": 165880585,
      "call_iv": 24.35,
      "put_iv": 21.06,
      "call_delta": 0.5522,
      "put_delta": -0.44
    },
    {
      "strike": 23250,
      "call_oi": 29717025,
      "put_oi": 14591005,
      "call_prev": 5853185,
      "put_prev": 1138215,
      "call_ltp": 40.6,
      "put_ltp": 65.6,
      "call_vol": 142779715,
      "put_vol": 92544725,
      "call_iv": 23.16,
      "put_iv": 20.02,
      "call_delta": 0.4116,
      "put_delta": -0.6023
    },
    {
      "strike": 23300,
      "call_oi": 29499730,
      "put_oi": 10621065,
      "call_prev": 9756175,
      "put_prev": 3505775,
      "call_ltp": 23.8,
      "put_ltp": 99.3,
      "call_vol": 134249050,
      "put_vol": 54287480,
      "call_iv": 23.19,
      "put_iv": 19.65,
      "call_delta": 0.28,
      "put_delta": -0.7545
    },
    {
      "strike": 23350,
      "call_oi": 13878475,
      "put_oi": 1984515,
      "call_prev": 4515160,
      "put_prev": 796445,
      "call_ltp": 12.9,
      "put_ltp": 138.1,
      "call_vol": 65414245,
      "put_vol": 12637885,
      "call_iv": 23.25,
      "put_iv": 19.9,
      "call_delta": 0.1715,
      "put_delta": -0.8663
    },
    {
      "strike": 23400,
      "call_oi": 16767790,
      "put_oi": 3453840,
      "call_prev": 9717305,
      "put_prev": 2155530,
      "call_ltp": 7.2,
      "put_ltp": 182.95,
      "call_vol": 70434000,
      "put_vol": 9854390,
      "call_iv": 24.11,
      "put_iv": 12.7,
      "call_delta": 0.1056,
      "put_delta": -0.9913
    },
    {
      "strike": 23450,
      "call_oi": 12051260,
      "put_oi": 678405,
      "call_prev": 4802200,
      "put_prev": 550810,
      "call_ltp": 4,
      "put_ltp": 228.7,
      "call_vol": 43905940,
      "put_vol": 1981200,
      "call_iv": 25.02,
      "put_iv": 0,
      "call_delta": 0.0623,
      "put_delta": -1
    },
    {
      "strike": 23500,
      "call_oi": 20310810,
      "put_oi": 3936205,
      "call_prev": 14453400,
      "put_prev": 3390985,
      "call_ltp": 2.65,
      "put_ltp": 277,
      "call_vol": 68396055,
      "put_vol": 4320550,
      "call_iv": 26.86,
      "put_iv": 0,
      "call_delta": 0.041,
      "put_delta": -1
    },
    {
      "strike": 23550,
      "call_oi": 8981180,
      "put_oi": 326820,
      "call_prev": 5271240,
      "put_prev": 322205,
      "call_ltp": 1.8,
      "put_ltp": 327.1,
      "call_vol": 46352150,
      "put_vol": 311090,
      "call_iv": 28.56,
      "put_iv": 0,
      "call_delta": 0.0272,
      "put_delta": -1
    },
    {
      "strike": 23600,
      "call_oi": 11735165,
      "put_oi": 1372735,
      "call_prev": 8728200,
      "put_prev": 1454245,
      "call_ltp": 1.35,
      "put_ltp": 375.45,
      "call_vol": 40147900,
      "put_vol": 451620,
      "call_iv": 30.76,
      "put_iv": 0,
      "call_delta": 0.02,
      "put_delta": -1
    },
    {
      "strike": 23650,
      "call_oi": 5256615,
      "put_oi": 137280,
      "call_prev": 4054115,
      "put_prev": 147810,
      "call_ltp": 1.1,
      "put_ltp": 425.8,
      "call_vol": 18551715,
      "put_vol": 73580,
      "call_iv": 32.71,
      "put_iv": 0,
      "call_delta": 0.0146,
      "put_delta": -1
    },
    {
      "strike": 23700,
      "call_oi": 12642175,
      "put_oi": 1743430,
      "call_prev": 10646285,
      "put_prev": 1815710,
      "call_ltp": 0.95,
      "put_ltp": 476.8,
      "call_vol": 37952850,
      "put_vol": 456365,
      "call_iv": 35.64,
      "put_iv": 0,
      "call_delta": 0.0128,
      "put_delta": -1
    },
    {
      "strike": 23750,
      "call_oi": 6481020,
      "put_oi": 106535,
      "call_prev": 3239925,
      "put_prev": 109135,
      "call_ltp": 0.9,
      "put_ltp": 527.9,
      "call_vol": 19448065,
      "put_vol": 26910,
      "call_iv": 38.57,
      "put_iv": 0,
      "call_delta": 0.0115,
      "put_delta": -1
    },
    {
      "strike": 23800,
      "call_oi": 11238240,
      "put_oi": 385450,
      "call_prev": 7473505,
      "put_prev": 406640,
      "call_ltp": 0.8,
      "put_ltp": 577.75,
      "call_vol": 29237000,
      "put_vol": 102635,
      "call_iv": 41.02,
      "put_iv": 0,
      "call_delta": 0.0097,
      "put_delta": -1
    },
    {
      "strike": 23850,
      "call_oi": 3987230,
      "put_oi": 105560,
      "call_prev": 2248285,
      "put_prev": 106665,
      "call_ltp": 0.75,
      "put_ltp": 638.15,
      "call_vol": 12341485,
      "put_vol": 11635,
      "call_iv": 43.95,
      "put_iv": 61.28,
      "call_delta": 0.0089,
      "put_delta": -0.9548
    },
    {
      "strike": 23900,
      "call_oi": 7260175,
      "put_oi": 350935,
      "call_prev": 5880095,
      "put_prev": 355030,
      "call_ltp": 0.75,
      "put_ltp": 675,
      "call_vol": 17904380,
      "put_vol": 35490,
      "call_iv": 46.88,
      "put_iv": 0,
      "call_delta": 0.0084,
      "put_delta": -1
    },
    {
      "strike": 23950,
      "call_oi": 3025295,
      "put_oi": 114790,
      "call_prev": 2510950,
      "put_prev": 115050,
      "call_ltp": 0.7,
      "put_ltp": 732.45,
      "call_vol": 7887425,
      "put_vol": 4485,
      "call_iv": 48.83,
      "put_iv": 0,
      "call_delta": 0.0069,
      "put_delta": -1
    },
    {
      "strike": 24000,
      "call_oi": 15207790,
      "put_oi": 707720,
      "call_prev": 16166540,
      "put_prev": 818155,
      "call_ltp": 0.6,
      "put_ltp": 774.6,
      "call_vol": 31609955,
      "put_vol": 176540,
      "call_iv": 50.78,
      "put_iv": 0,
      "call_delta": 0.0058,
      "put_delta": -1
    },
    {
      "strike": 24050,
      "call_oi": 2265835,
      "put_oi": 86385,
      "call_prev": 1755260,
      "put_prev": 86580,
      "call_ltp": 0.6,
      "put_ltp": 831.05,
      "call_vol": 4745000,
      "put_vol": 2080,
      "call_iv": 53.71,
      "put_iv": 0,
      "call_delta": 0.0055,
      "put_delta": -1
    },
    {
      "strike": 24100,
      "call_oi": 4807660,
      "put_oi": 132145,
      "call_prev": 4939480,
      "put_prev": 134680,
      "call_ltp": 0.55,
      "put_ltp": 887.5,
      "call_vol": 12078690,
      "put_vol": 30680,
      "call_iv": 56.64,
      "put_iv": 75.68,
      "call_delta": 0.0054,
      "put_delta": -0.9716
    },
    {
      "strike": 24150,
      "call_oi": 1361945,
      "put_oi": 25220,
      "call_prev": 1454830,
      "put_prev": 25805,
      "call_ltp": 0.55,
      "put_ltp": 900,
      "call_vol": 3023150,
      "put_vol": 2405,
      "call_iv": 58.59,
      "put_iv": 0,
      "call_delta": 0.0046,
      "put_delta": -1
    },
    {
      "strike": 24200,
      "call_oi": 6725095,
      "put_oi": 79040,
      "call_prev": 7403305,
      "put_prev": 86385,
      "call_ltp": 0.5,
      "put_ltp": 985.05,
      "call_vol": 15119845,
      "put_vol": 16900,
      "call_iv": 60.55,
      "put_iv": 78.86,
      "call_delta": 0.004,
      "put_delta": -0.9788
    },
    {
      "strike": 24250,
      "call_oi": 1362660,
      "put_oi": 19890,
      "call_prev": 1042990,
      "put_prev": 20475,
      "call_ltp": 0.5,
      "put_ltp": 1032,
      "call_vol": 2669030,
      "put_vol": 4030,
      "call_iv": 64.45,
      "put_iv": 0,
      "call_delta": 0.0045,
      "put_delta": -1
    },
    {
      "strike": 24300,
      "call_oi": 3119155,
      "put_oi": 56290,
      "call_prev": 3467945,
      "put_prev": 57980,
      "call_ltp": 0.5,
      "put_ltp": 1080,
      "call_vol": 7875985,
      "put_vol": 6110,
      "call_iv": 66.41,
      "put_iv": 0,
      "call_delta": 0.004,
      "put_delta": -1
    },
    {
      "strike": 24350,
      "call_oi": 1386970,
      "put_oi": 9100,
      "call_prev": 1061255,
      "put_prev": 9035,
      "call_ltp": 0.45,
      "put_ltp": 1213.9,
      "call_vol": 2493985,
      "put_vol": 0,
      "call_iv": 68.36,
      "put_iv": 175.72,
      "call_delta": 0.0035,
      "put_delta": -0.8486
    },
    {
      "strike": 24400,
      "call_oi": 2544490,
      "put_oi": 55185,
      "call_prev": 3157765,
      "put_prev": 59085,
      "call_ltp": 0.45,
      "put_ltp": 1178.95,
      "call_vol": 4753840,
      "put_vol": 6695,
      "call_iv": 71.29,
      "put_iv": 0,
      "call_delta": 0.0035,
      "put_delta": -1
    },
    {
      "strike": 24450,
      "call_oi": 933205,
      "put_oi": 5460,
      "call_prev": 817245,
      "put_prev": 5525,
      "call_ltp": 0.45,
      "put_ltp": 1340,
      "call_vol": 1412775,
      "put_vol": 0,
      "call_iv": 74.22,
      "put_iv": 204.1,
      "call_delta": 0.0035,
      "put_delta": -0.831
    },
    {
      "strike": 24500,
      "call_oi": 6407505,
      "put_oi": 177060,
      "call_prev": 9379760,
      "put_prev": 201890,
      "call_ltp": 0.4,
      "put_ltp": 1279.05,
      "call_vol": 13278720,
      "put_vol": 39260,
      "call_iv": 76.17,
      "put_iv": 0,
      "call_delta": 0.0032,
      "put_delta": -1
    },
    {
      "strike": 24550,
      "call_oi": 958750,
      "put_oi": 2080,
      "call_prev": 1439360,
      "put_prev": 2080,
      "call_ltp": 0.4,
      "put_ltp": 1315.45,
      "call_vol": 1899170,
      "put_vol": 130,
      "call_iv": 78.13,
      "put_iv": 0,
      "call_delta": 0.0029,
      "put_delta": -1
    },
    {
      "strike": 24600,
      "call_oi": 1738360,
      "put_oi": 10465,
      "call_prev": 2640105,
      "put_prev": 10465,
      "call_ltp": 0.4,
      "put_ltp": 1355,
      "call_vol": 3805230,
      "put_vol": 195,
      "call_iv": 80.08,
      "put_iv": 0,
      "call_delta": 0.0026,
      "put_delta": -1
    },
    {
      "strike": 24650,
      "call_oi": 905125,
      "put_oi": 4290,
      "call_prev": 973115,
      "put_prev": 4290,
      "call_ltp": 0.4,
      "put_ltp": 1410,
      "call_vol": 519740,
      "put_vol": 0,
      "call_iv": 83.98,
      "put_iv": 0,
      "call_delta": 0.0029,
      "put_delta": -1
    },
    {
      "strike": 24700,
      "call_oi": 1952860,
      "put_oi": 3445,
      "call_prev": 2546765,
      "put_prev": 4680,
      "call_ltp": 0.4,
      "put_ltp": 1478.85,
      "call_vol": 2517125,
      "put_vol": 1950,
      "call_iv": 85.94,
      "put_iv": 0,
      "call_delta": 0.0027,
      "put_delta": -1
    },
    {
      "strike": 24750,
      "call_oi": 890110,
      "put_oi": 195,
      "call_prev": 988260,
      "put_prev": 195,
      "call_ltp": 0.4,
      "put_ltp": 1331.9,
      "call_vol": 917475,
      "put_vol": 0,
      "call_iv": 87.89,
      "put_iv": 0,
      "call_delta": 0.0024,
      "put_delta": -1
    },
    {
      "strike": 24800,
      "call_oi": 2155790,
      "put_oi": 31460,
      "call_prev": 2794025,
      "put_prev": 34190,
      "call_ltp": 0.4,
      "put_ltp": 1585.4,
      "call_vol": 2150785,
      "put_vol": 7930,
      "call_iv": 89.84,
      "put_iv": 112.79,
      "call_delta": 0.0023,
      "put_delta": -0.988
    },
    {
      "strike": 24850,
      "call_oi": 717535,
      "put_oi": 390,
      "call_prev": 747240,
      "put_prev": 2080,
      "call_ltp": 0.4,
      "put_ltp": 1330.25,
      "call_vol": 272415,
      "put_vol": 0,
      "call_iv": 93.75,
      "put_iv": 0,
      "call_delta": 0.0025,
      "put_delta": -1
    },
    {
      "strike": 24900,
      "call_oi": 1375140,
      "put_oi": 17550,
      "call_prev": 1575795,
      "put_prev": 17680,
      "call_ltp": 0.35,
      "put_ltp": 1665.85,
      "call_vol": 977470,
      "put_vol": 1235,
      "call_iv": 93.75,
      "put_iv": 0,
      "call_delta": 0.0019,
      "put_delta": -1
    },
    {
      "strike": 24950,
      "call_oi": 422630,
      "put_oi": 650,
      "call_prev": 595400,
      "put_prev": 715,
      "call_ltp": 0.35,
      "put_ltp": 1552.65,
      "call_vol": 548405,
      "put_vol": 0,
      "call_iv": 97.66,
      "put_iv": 0,
      "call_delta": 0.0022,
      "put_delta": -1
    },
    {
      "strike": 25000,
      "call_oi": 4821635,
      "put_oi": 161525,
      "call_prev": 6112275,
      "put_prev": 168415,
      "call_ltp": 0.3,
      "put_ltp": 1785.85,
      "call_vol": 6126835,
      "put_vol": 10790,
      "call_iv": 97.66,
      "put_iv": 126.95,
      "call_delta": 0.0017,
      "put_delta": -0.9877
    },
    {
      "strike": 25050,
      "call_oi": 329030,
      "put_oi": 1170,
      "call_prev": 471705,
      "put_prev": 1105,
      "call_ltp": 0.4,
      "put_ltp": 1940,
      "call_vol": 523835,
      "put_vol": 0,
      "call_iv": 103.52,
      "put_iv": 263.98,
      "call_delta": 0.0023,
      "put_delta": -0.8606
    },
    {
      "strike": 25100,
      "call_oi": 728130,
      "put_oi": 455,
      "call_prev": 749970,
      "put_prev": 455,
      "call_ltp": 0.3,
      "put_ltp": 1935,
      "call_vol": 595270,
      "put_vol": 0,
      "call_iv": 105.47,
      "put_iv": 219.24,
      "call_delta": 0.0021,
      "put_delta": -0.912
    },
    {
      "strike": 25150,
      "call_oi": 446225,
      "put_oi": 585,
      "call_prev": 449085,
      "put_prev": 520,
      "call_ltp": 0.35,
      "put_ltp": 1981.25,
      "call_vol": 169065,
      "put_vol": 0,
      "call_iv": 105.47,
      "put_iv": 219.73,
      "call_delta": 0.0017,
      "put_delta": -0.917
    },
    {
      "strike": 25200,
      "call_oi": 1545245,
      "put_oi": 5655,
      "call_prev": 1559935,
      "put_prev": 5590,
      "call_ltp": 0.35,
      "put_ltp": 1997.2,
      "call_vol": 582140,
      "put_vol": 130,
      "call_iv": 109.38,
      "put_iv": 174.56,
      "call_delta": 0.0019,
      "put_delta": -0.9641
    },
    {
      "strike": 25250,
      "call_oi": 598260,
      "put_oi": 325,
      "call_prev": 595140,
      "put_prev": 325,
      "call_ltp": 0.3,
      "put_ltp": 1836.85,
      "call_vol": 150865,
      "put_vol": 0,
      "call_iv": 109.38,
      "put_iv": 0,
      "call_delta": 0.0015,
      "put_delta": -1
    },
    {
      "strike": 25300,
      "call_oi": 2155920,
      "put_oi": 195,
      "call_prev": 2192905,
      "put_prev": 260,
      "call_ltp": 0.3,
      "put_ltp": 2080,
      "call_vol": 881530,
      "put_vol": 195,
      "call_iv": 113.28,
      "put_iv": 0,
      "call_delta": 0.0017,
      "put_delta": -1
    },
    {
      "strike": 25350,
      "call_oi": 785590,
      "put_oi": 520,
      "call_prev": 808145,
      "put_prev": 520,
      "call_ltp": 0.35,
      "put_ltp": 2067,
      "call_vol": 243490,
      "put_vol": 0,
      "call_iv": 117.19,
      "put_iv": 0,
      "call_delta": 0.0019,
      "put_delta": -1
    },
    {
      "strike": 25400,
      "call_oi": 934375,
      "put_oi": 1690,
      "call_prev": 956540,
      "put_prev": 1690,
      "call_ltp": 0.3,
      "put_ltp": 2172.5,
      "call_vol": 215540,
      "put_vol": 130,
      "call_iv": 117.19,
      "put_iv": 0,
      "call_delta": 0.0015,
      "put_delta": -1
    },
    {
      "strike": 25450,
      "call_oi": 281580,
      "put_oi": 130,
      "call_prev": 323050,
      "put_prev": 130,
      "call_ltp": 0.25,
      "put_ltp": 2239.4,
      "call_vol": 140855,
      "put_vol": 65,
      "call_iv": 117.19,
      "put_iv": 173.83,
      "call_delta": 0.0012,
      "put_delta": -0.9787
    },
    {
      "strike": 25500,
      "call_oi": 2422875,
      "put_oi": 56420,
      "call_prev": 3074110,
      "put_prev": 58890,
      "call_ltp": 0.3,
      "put_ltp": 2260.1,
      "call_vol": 2400125,
      "put_vol": 2730,
      "call_iv": 121.09,
      "put_iv": 0,
      "call_delta": 0.0014,
      "put_delta": -1
    },
    {
      "strike": 25550,
      "call_oi": 213850,
      "put_oi": 1040,
      "call_prev": 268255,
      "put_prev": 1040,
      "call_ltp": 0.3,
      "put_ltp": 2220,
      "call_vol": 246025,
      "put_vol": 0,
      "call_iv": 125,
      "put_iv": 0,
      "call_delta": 0.0016,
      "put_delta": -1
    },
    {
      "strike": 25600,
      "call_oi": 425230,
      "put_oi": 2080,
      "call_prev": 452270,
      "put_prev": 2080,
      "call_ltp": 0.3,
      "put_ltp": 2435,
      "call_vol": 382525,
      "put_vol": 0,
      "call_iv": 125,
      "put_iv": 260.01,
      "call_delta": 0.0013,
      "put_delta": -0.923
    },
    {
      "strike": 25650,
      "call_oi": 97240,
      "put_oi": 780,
      "call_prev": 70980,
      "put_prev": 780,
      "call_ltp": 0.3,
      "put_ltp": 2410,
      "call_vol": 78845,
      "put_vol": 520,
      "call_iv": 128.91,
      "put_iv": 0,
      "call_delta": 0.0014,
      "put_delta": -1
    },
    {
      "strike": 25700,
      "call_oi": 225030,
      "put_oi": 65,
      "call_prev": 263835,
      "put_prev": 130,
      "call_ltp": 0.3,
      "put_ltp": 2272.7,
      "call_vol": 429065,
      "put_vol": 0,
      "call_iv": 128.91,
      "put_iv": 0,
      "call_delta": 0.0012,
      "put_delta": -1
    },
    {
      "strike": 25750,
      "call_oi": 70005,
      "put_oi": 65,
      "call_prev": 57590,
      "put_prev": 65,
      "call_ltp": 0.3,
      "put_ltp": 2527.65,
      "call_vol": 86125,
      "put_vol": 0,
      "call_iv": 132.81,
      "put_iv": 0,
      "call_delta": 0.0013,
      "put_delta": -1
    },
    {
      "strike": 25800,
      "call_oi": 225355,
      "put_oi": 455,
      "call_prev": 238940,
      "put_prev": 455,
      "call_ltp": 0.3,
      "put_ltp": 2666.9,
      "call_vol": 236925,
      "put_vol": 0,
      "call_iv": 136.72,
      "put_iv": 309.08,
      "call_delta": 0.0014,
      "put_delta": -0.9007
    },
    {
      "strike": 25850,
      "call_oi": 83135,
      "put_oi": 325,
      "call_prev": 73190,
      "put_prev": 325,
      "call_ltp": 0.25,
      "put_ltp": 2678.65,
      "call_vol": 35360,
      "put_vol": 65,
      "call_iv": 136.72,
      "put_iv": 271.36,
      "call_delta": 0.0012,
      "put_delta": -0.9335
    },
    {
      "strike": 25900,
      "call_oi": 127400,
      "put_oi": 65,
      "call_prev": 150670,
      "put_prev": 65,
      "call_ltp": 0.25,
      "put_ltp": 2672,
      "call_vol": 90415,
      "put_vol": 65,
      "call_iv": 136.72,
      "put_iv": 0,
      "call_delta": 0.001,
      "put_delta": -1
    },
    {
      "strike": 25950,
      "call_oi": 66625,
      "put_oi": 0,
      "call_prev": 58955,
      "put_prev": 0,
      "call_ltp": 0.25,
      "put_ltp": 0,
      "call_vol": 44720,
      "put_vol": 0,
      "call_iv": 140.63,
      "put_iv": 0,
      "call_delta": 0.0011,
      "put_delta": -1
    },
    {
      "strike": 26000,
      "call_oi": 1252355,
      "put_oi": 30290,
      "call_prev": 1525810,
      "put_prev": 43745,
      "call_ltp": 0.25,
      "put_ltp": 2786,
      "call_vol": 997620,
      "put_vol": 14495,
      "call_iv": 140.63,
      "put_iv": 192.38,
      "call_delta": 0.0009,
      "put_delta": -0.9881
    },
    {
      "strike": 26050,
      "call_oi": 162435,
      "put_oi": 65,
      "call_prev": 166205,
      "put_prev": 0,
      "call_ltp": 0.25,
      "put_ltp": 2786.75,
      "call_vol": 158080,
      "put_vol": 0,
      "call_iv": 144.53,
      "put_iv": 0,
      "call_delta": 0.0011,
      "put_delta": -1
    },
    {
      "strike": 26100,
      "call_oi": 843635,
      "put_oi": 2080,
      "call_prev": 905905,
      "put_prev": 2210,
      "call_ltp": 0.25,
      "put_ltp": 2880,
      "call_vol": 608465,
      "put_vol": 325,
      "call_iv": 148.44,
      "put_iv": 0,
      "call_delta": 0.0012,
      "put_delta": -1
    }
  ]
}