{
  "symbol": "NIFTY50",
  "expiry": "2026-06-16",
  "date": "2026-06-11",
  "time": "13:49:44",
  "spot": 23228.2,
  "strikes": [
    {
      "strike": 21200,
      "call_oi": 130,
      "put_oi": 10010065,
      "call_prev": 65,
      "put_prev": 8634470,
      "call_ltp": 2074.4,
      "put_ltp": 1.55,
      "call_vol": 650,
      "put_vol": 8926320,
      "call_iv": 50.42,
      "put_iv": 31.01,
      "call_delta": 0.9425,
      "put_delta": -0.0057
    },
    {
      "strike": 21250,
      "call_oi": 65,
      "put_oi": 457210,
      "call_prev": 65,
      "put_prev": 367055,
      "call_ltp": 2258.65,
      "put_ltp": 1.55,
      "call_vol": 0,
      "put_vol": 1544465,
      "call_iv": 90.97,
      "put_iv": 30.27,
      "call_delta": 0.8128,
      "put_delta": -0.0058
    },
    {
      "strike": 21300,
      "call_oi": 65,
      "put_oi": 1491815,
      "call_prev": 65,
      "put_prev": 1378455,
      "call_ltp": 2212.05,
      "put_ltp": 1.6,
      "call_vol": 0,
      "put_vol": 2141425,
      "call_iv": 89.95,
      "put_iv": 29.66,
      "call_delta": 0.8092,
      "put_delta": -0.006
    },
    {
      "strike": 21350,
      "call_oi": 65,
      "put_oi": 86645,
      "call_prev": 65,
      "put_prev": 71240,
      "call_ltp": 2150.8,
      "put_ltp": 1.65,
      "call_vol": 0,
      "put_vol": 773565,
      "call_iv": 86.96,
      "put_iv": 29.05,
      "call_delta": 0.8102,
      "put_delta": -0.0063
    },
    {
      "strike": 21400,
      "call_oi": 130,
      "put_oi": 1049425,
      "call_prev": 130,
      "put_prev": 943475,
      "call_ltp": 1932.8,
      "put_ltp": 1.65,
      "call_vol": 0,
      "put_vol": 1690585,
      "call_iv": 59.57,
      "put_iv": 28.32,
      "call_delta": 0.8869,
      "put_delta": -0.0064
    },
    {
      "strike": 21450,
      "call_oi": 65,
      "put_oi": 143000,
      "call_prev": 65,
      "put_prev": 85865,
      "call_ltp": 2063.25,
      "put_ltp": 1.75,
      "call_vol": 0,
      "put_vol": 958620,
      "call_iv": 85.74,
      "put_iv": 27.83,
      "call_delta": 0.8004,
      "put_delta": -0.0069
    },
    {
      "strike": 21500,
      "call_oi": 1170,
      "put_oi": 4130295,
      "call_prev": 1235,
      "put_prev": 3030105,
      "call_ltp": 1875.9,
      "put_ltp": 1.75,
      "call_vol": 0,
      "put_vol": 7650370,
      "call_iv": 64.54,
      "put_iv": 27.1,
      "call_delta": 0.8557,
      "put_delta": -0.0071
    },
    {
      "strike": 21550,
      "call_oi": 65,
      "put_oi": 120055,
      "call_prev": 65,
      "put_prev": 92300,
      "call_ltp": 1963.7,
      "put_ltp": 1.85,
      "call_vol": 0,
      "put_vol": 987090,
      "call_iv": 82.82,
      "put_iv": 26.61,
      "call_delta": 0.7943,
      "put_delta": -0.0077
    },
    {
      "strike": 21600,
      "call_oi": 65,
      "put_oi": 885690,
      "call_prev": 65,
      "put_prev": 718250,
      "call_ltp": 1914.3,
      "put_ltp": 1.9,
      "call_vol": 0,
      "put_vol": 2394600,
      "call_iv": 81.6,
      "put_iv": 25.88,
      "call_delta": 0.7903,
      "put_delta": -0.0079
    },
    {
      "strike": 21650,
      "call_oi": 65,
      "put_oi": 157755,
      "call_prev": 65,
      "put_prev": 129285,
      "call_ltp": 2357.4,
      "put_ltp": 1.95,
      "call_vol": 0,
      "put_vol": 1066455,
      "call_iv": 135.33,
      "put_iv": 25.27,
      "call_delta": 0.6996,
      "put_delta": -0.0083
    },
    {
      "strike": 21700,
      "call_oi": 65,
      "put_oi": 938730,
      "call_prev": 65,
      "put_prev": 736320,
      "call_ltp": 1802.5,
      "put_ltp": 2,
      "call_vol": 0,
      "put_vol": 4513210,
      "call_iv": 77.09,
      "put_iv": 24.66,
      "call_delta": 0.7877,
      "put_delta": -0.0088
    },
    {
      "strike": 21750,
      "call_oi": 65,
      "put_oi": 309790,
      "call_prev": 65,
      "put_prev": 272350,
      "call_ltp": 1756.15,
      "put_ltp": 2.05,
      "call_vol": 0,
      "put_vol": 1755130,
      "call_iv": 75.64,
      "put_iv": 24.05,
      "call_delta": 0.7847,
      "put_delta": -0.0093
    },
    {
      "strike": 21800,
      "call_oi": 65,
      "put_oi": 2735590,
      "call_prev": 65,
      "put_prev": 2635360,
      "call_ltp": 1703.65,
      "put_ltp": 2.15,
      "call_vol": 0,
      "put_vol": 5984745,
      "call_iv": 73.82,
      "put_iv": 23.44,
      "call_delta": 0.782,
      "put_delta": -0.0099
    },
    {
      "strike": 21850,
      "call_oi": 65,
      "put_oi": 203840,
      "call_prev": 65,
      "put_prev": 177970,
      "call_ltp": 1654.45,
      "put_ltp": 2.25,
      "call_vol": 0,
      "put_vol": 2118025,
      "call_iv": 72.4,
      "put_iv": 22.83,
      "call_delta": 0.7781,
      "put_delta": -0.0105
    },
    {
      "strike": 21900,
      "call_oi": 195,
      "put_oi": 1147120,
      "call_prev": 195,
      "put_prev": 986765,
      "call_ltp": 1451,
      "put_ltp": 2.35,
      "call_vol": 0,
      "put_vol": 6305975,
      "call_iv": 49.74,
      "put_iv": 22.22,
      "call_delta": 0.8521,
      "put_delta": -0.0113
    },
    {
      "strike": 21950,
      "call_oi": 65,
      "put_oi": 312845,
      "call_prev": 65,
      "put_prev": 295490,
      "call_ltp": 1571.5,
      "put_ltp": 2.55,
      "call_vol": 0,
      "put_vol": 2020005,
      "call_iv": 71.43,
      "put_iv": 21.67,
      "call_delta": 0.7644,
      "put_delta": -0.0123
    },
    {
      "strike": 22000,
      "call_oi": 51805,
      "put_oi": 7884240,
      "call_prev": 52065,
      "put_prev": 7100275,
      "call_ltp": 1245,
      "put_ltp": 2.75,
      "call_vol": 18915,
      "put_vol": 21973185,
      "call_iv": 23.32,
      "put_iv": 21.12,
      "call_delta": 0.9777,
      "put_delta": -0.0134
    },
    {
      "strike": 22050,
      "call_oi": 130,
      "put_oi": 425815,
      "call_prev": 195,
      "put_prev": 415220,
      "call_ltp": 1151.6,
      "put_ltp": 2.85,
      "call_vol": 195,
      "put_vol": 2728440,
      "call_iv": 0,
      "put_iv": 20.39,
      "call_delta": 1,
      "put_delta": -0.0139
    },
    {
      "strike": 22100,
      "call_oi": 520,
      "put_oi": 2517710,
      "call_prev": 455,
      "put_prev": 1936935,
      "call_ltp": 1170,
      "put_ltp": 2.95,
      "call_vol": 130,
      "put_vol": 10987210,
      "call_iv": 30.61,
      "put_iv": 19.78,
      "call_delta": 0.921,
      "put_delta": -0.015
    },
    {
      "strike": 22150,
      "call_oi": 260,
      "put_oi": 928720,
      "call_prev": 195,
      "put_prev": 628550,
      "call_ltp": 1048,
      "put_ltp": 3.2,
      "call_vol": 130,
      "put_vol": 4814550,
      "call_iv": 0,
      "put_iv": 19.29,
      "call_delta": 1,
      "put_delta": -0.0169
    },
    {
      "strike": 22200,
      "call_oi": 2210,
      "put_oi": 2816320,
      "call_prev": 1820,
      "put_prev": 2341625,
      "call_ltp": 1040,
      "put_ltp": 3.55,
      "call_vol": 3705,
      "put_vol": 13976625,
      "call_iv": 14.16,
      "put_iv": 18.8,
      "call_delta": 0.997,
      "put_delta": -0.0189
    },
    {
      "strike": 22250,
      "call_oi": 2275,
      "put_oi": 1285050,
      "call_prev": 1950,
      "put_prev": 641550,
      "call_ltp": 1064.55,
      "put_ltp": 3.95,
      "call_vol": 715,
      "put_vol": 6205940,
      "call_iv": 35.74,
      "put_iv": 18.31,
      "call_delta": 0.8541,
      "put_delta": -0.0213
    },
    {
      "strike": 22300,
      "call_oi": 2990,
      "put_oi": 5288985,
      "call_prev": 2080,
      "put_prev": 2513225,
      "call_ltp": 1029,
      "put_ltp": 4.3,
      "call_vol": 5590,
      "put_vol": 22527375,
      "call_iv": 36.73,
      "put_iv": 17.76,
      "call_delta": 0.8352,
      "put_delta": -0.0237
    },
    {
      "strike": 22350,
      "call_oi": 4615,
      "put_oi": 1119365,
      "call_prev": 4940,
      "put_prev": 693225,
      "call_ltp": 969.8,
      "put_ltp": 5.05,
      "call_vol": 1495,
      "put_vol": 7760675,
      "call_iv": 34.09,
      "put_iv": 17.33,
      "call_delta": 0.8392,
      "put_delta": -0.0274
    },
    {
      "strike": 22400,
      "call_oi": 8515,
      "put_oi": 3710525,
      "call_prev": 6825,
      "put_prev": 2410785,
      "call_ltp": 843,
      "put_ltp": 5.8,
      "call_vol": 10270,
      "put_vol": 17133025,
      "call_iv": 15.69,
      "put_iv": 16.91,
      "call_delta": 0.9772,
      "put_delta": -0.0317
    },
    {
      "strike": 22450,
      "call_oi": 2405,
      "put_oi": 1088945,
      "call_prev": 845,
      "put_prev": 731900,
      "call_ltp": 823.25,
      "put_ltp": 7.05,
      "call_vol": 5395,
      "put_vol": 8978515,
      "call_iv": 23.8,
      "put_iv": 16.66,
      "call_delta": 0.8937,
      "put_delta": -0.0383
    },
    {
      "strike": 22500,
      "call_oi": 270660,
      "put_oi": 6471985,
      "call_prev": 271960,
      "put_prev": 5819060,
      "call_ltp": 754.2,
      "put_ltp": 8.5,
      "call_vol": 283530,
      "put_vol": 32809400,
      "call_iv": 18.42,
      "put_iv": 16.33,
      "call_delta": 0.9332,
      "put_delta": -0.0455
    },
    {
      "strike": 22550,
      "call_oi": 18915,
      "put_oi": 1348555,
      "call_prev": 15340,
      "put_prev": 1051895,
      "call_ltp": 697.45,
      "put_ltp": 10.3,
      "call_vol": 33085,
      "put_vol": 10808395,
      "call_iv": 15.2,
      "put_iv": 16.08,
      "call_delta": 0.9546,
      "put_delta": -0.0549
    },
    {
      "strike": 22600,
      "call_oi": 51870,
      "put_oi": 3879460,
      "call_prev": 40170,
      "put_prev": 3256500,
      "call_ltp": 661.75,
      "put_ltp": 12.55,
      "call_vol": 143065,
      "put_vol": 23348975,
      "call_iv": 18.16,
      "put_iv": 15.81,
      "call_delta": 0.9057,
      "put_delta": -0.066
    },
    {
      "strike": 22650,
      "call_oi": 41340,
      "put_oi": 2115815,
      "call_prev": 30615,
      "put_prev": 1060865,
      "call_ltp": 609.05,
      "put_ltp": 15.5,
      "call_vol": 124670,
      "put_vol": 16254095,
      "call_iv": 16.51,
      "put_iv": 15.56,
      "call_delta": 0.9083,
      "put_delta": -0.0794
    },
    {
      "strike": 22700,
      "call_oi": 120185,
      "put_oi": 4112420,
      "call_prev": 106145,
      "put_prev": 2744430,
      "call_ltp": 568.65,
      "put_ltp": 19.4,
      "call_vol": 498160,
      "put_vol": 30191330,
      "call_iv": 17.3,
      "put_iv": 15.44,
      "call_delta": 0.8774,
      "put_delta": -0.0968
    },
    {
      "strike": 22750,
      "call_oi": 48880,
      "put_oi": 2709395,
      "call_prev": 35360,
      "put_prev": 1578460,
      "call_ltp": 519.75,
      "put_ltp": 23.8,
      "call_vol": 212810,
      "put_vol": 19343675,
      "call_iv": 16.36,
      "put_iv": 15.23,
      "call_delta": 0.8674,
      "put_delta": -0.1159
    },
    {
      "strike": 22800,
      "call_oi": 227630,
      "put_oi": 4577495,
      "call_prev": 135720,
      "put_prev": 3434470,
      "call_ltp": 476,
      "put_ltp": 29.45,
      "call_vol": 1842880,
      "put_vol": 40375270,
      "call_iv": 16.2,
      "put_iv": 15.06,
      "call_delta": 0.8435,
      "put_delta": -0.1392
    },
    {
      "strike": 22850,
      "call_oi": 70980,
      "put_oi": 2488850,
      "call_prev": 35165,
      "put_prev": 2479555,
      "call_ltp": 434.6,
      "put_ltp": 36,
      "call_vol": 633035,
      "put_vol": 20235670,
      "call_iv": 16.14,
      "put_iv": 14.88,
      "call_delta": 0.8155,
      "put_delta": -0.1655
    },
    {
      "strike": 22900,
      "call_oi": 310180,
      "put_oi": 4470245,
      "call_prev": 185640,
      "put_prev": 2397460,
      "call_ltp": 391.3,
      "put_ltp": 44.3,
      "call_vol": 4060615,
      "put_vol": 41474940,
      "call_iv": 15.72,
      "put_iv": 14.76,
      "call_delta": 0.7892,
      "put_delta": -0.1962
    },
    {
      "strike": 22950,
      "call_oi": 166140,
      "put_oi": 2425930,
      "call_prev": 43550,
      "put_prev": 845845,
      "call_ltp": 353,
      "put_ltp": 53.7,
      "call_vol": 2683980,
      "put_vol": 28548650,
      "call_iv": 15.7,
      "put_iv": 14.54,
      "call_delta": 0.754,
      "put_delta": -0.2295
    },
    {
      "strike": 23000,
      "call_oi": 1547910,
      "put_oi": 9890270,
      "call_prev": 1164020,
      "put_prev": 4633395,
      "call_ltp": 312,
      "put_ltp": 65.3,
      "call_vol": 27286675,
      "put_vol": 87633715,
      "call_iv": 15.17,
      "put_iv": 14.43,
      "call_delta": 0.722,
      "put_delta": -0.2683
    },
    {
      "strike": 23050,
      "call_oi": 558870,
      "put_oi": 3283020,
      "call_prev": 128960,
      "put_prev": 808405,
      "call_ltp": 275.3,
      "put_ltp": 78.35,
      "call_vol": 15242760,
      "put_vol": 38406420,
      "call_iv": 15.04,
      "put_iv": 14.22,
      "call_delta": 0.681,
      "put_delta": -0.3095
    },
    {
      "strike": 23100,
      "call_oi": 2014610,
      "put_oi": 9625135,
      "call_prev": 879320,
      "put_prev": 2582645,
      "call_ltp": 240.3,
      "put_ltp": 93.9,
      "call_vol": 81287115,
      "put_vol": 112499855,
      "call_iv": 14.76,
      "put_iv": 14.1,
      "call_delta": 0.6388,
      "put_delta": -0.3553
    },
    {
      "strike": 23150,
      "call_oi": 1573390,
      "put_oi": 5378880,
      "call_prev": 486785,
      "put_prev": 1185405,
      "call_ltp": 207.9,
      "put_ltp": 111,
      "call_vol": 60606000,
      "put_vol": 69079855,
      "call_iv": 14.65,
      "put_iv": 13.86,
      "call_delta": 0.5916,
      "put_delta": -0.4037
    },
    {
      "strike": 23200,
      "call_oi": 5627700,
      "put_oi": 10376015,
      "call_prev": 3701815,
      "put_prev": 4955535,
      "call_ltp": 177.4,
      "put_ltp": 131.55,
      "call_vol": 109558475,
      "put_vol": 108456465,
      "call_iv": 14.39,
      "put_iv": 13.74,
      "call_delta": 0.5431,
      "put_delta": -0.4552
    },
    {
      "strike": 23250,
      "call_oi": 2914405,
      "put_oi": 4047745,
      "call_prev": 1915160,
      "put_prev": 1687920,
      "call_ltp": 150.6,
      "put_ltp": 153.55,
      "call_vol": 62816260,
      "put_vol": 52337220,
      "call_iv": 14.24,
      "put_iv": 13.58,
      "call_delta": 0.4928,
      "put_delta": -0.5079
    },
    {
      "strike": 23300,
      "call_oi": 6658600,
      "put_oi": 6727240,
      "call_prev": 5630430,
      "put_prev": 3837990,
      "call_ltp": 125.6,
      "put_ltp": 179.1,
      "call_vol": 106960685,
      "put_vol": 71416085,
      "call_iv": 14.07,
      "put_iv": 13.42,
      "call_delta": 0.4411,
      "put_delta": -0.562
    },
    {
      "strike": 23350,
      "call_oi": 2903940,
      "put_oi": 1513330,
      "call_prev": 2728505,
      "put_prev": 1126320,
      "call_ltp": 103.5,
      "put_ltp": 207.05,
      "call_vol": 47021065,
      "put_vol": 16158285,
      "call_iv": 13.92,
      "put_iv": 13.18,
      "call_delta": 0.3896,
      "put_delta": -0.6168
    },
    {
      "strike": 23400,
      "call_oi": 5836350,
      "put_oi": 2682225,
      "call_prev": 6021925,
      "put_prev": 2282215,
      "call_ltp": 84.35,
      "put_ltp": 237.65,
      "call_vol": 70119205,
      "put_vol": 20278375,
      "call_iv": 13.79,
      "put_iv": 13.06,
      "call_delta": 0.3387,
      "put_delta": -0.67
    },
    {
      "strike": 23450,
      "call_oi": 2316795,
      "put_oi": 521690,
      "call_prev": 2079415,
      "put_prev": 399555,
      "call_ltp": 67.5,
      "put_ltp": 271.1,
      "call_vol": 31639140,
      "put_vol": 3450070,
      "call_iv": 13.66,
      "put_iv": 12.73,
      "call_delta": 0.2906,
      "put_delta": -0.7235
    },
    {
      "strike": 23500,
      "call_oi": 6722235,
      "put_oi": 2435160,
      "call_prev": 6549140,
      "put_prev": 1991080,
      "call_ltp": 53.65,
      "put_ltp": 306.45,
      "call_vol": 72863570,
      "put_vol": 9829105,
      "call_iv": 13.57,
      "put_iv": 12.74,
      "call_delta": 0.2453,
      "put_delta": -0.769
    },
    {
      "strike": 23550,
      "call_oi": 2139150,
      "put_oi": 246675,
      "call_prev": 1398800,
      "put_prev": 153725,
      "call_ltp": 41.75,
      "put_ltp": 344.1,
      "call_vol": 26304720,
      "put_vol": 904345,
      "call_iv": 13.46,
      "put_iv": 12.37,
      "call_delta": 0.2037,
      "put_delta": -0.8165
    },
    {
      "strike": 23600,
      "call_oi": 4869670,
      "put_oi": 658190,
      "call_prev": 3438695,
      "put_prev": 626860,
      "call_ltp": 32.25,
      "put_ltp": 384.65,
      "call_vol": 45859970,
      "put_vol": 2014285,
      "call_iv": 13.4,
      "put_iv": 12.12,
      "call_delta": 0.1669,
      "put_delta": -0.8578
    },
    {
      "strike": 23650,
      "call_oi": 1872000,
      "put_oi": 216515,
      "call_prev": 1081145,
      "put_prev": 194935,
      "call_ltp": 24.7,
      "put_ltp": 425.95,
      "call_vol": 23937095,
      "put_vol": 374855,
      "call_iv": 13.37,
      "put_iv": 11.69,
      "call_delta": 0.135,
      "put_delta": -0.8968
    },
    {
      "strike": 23700,
      "call_oi": 6075355,
      "put_oi": 496795,
      "call_prev": 3541525,
      "put_prev": 534755,
      "call_ltp": 18.75,
      "put_ltp": 468.3,
      "call_vol": 48668880,
      "put_vol": 746135,
      "call_iv": 13.37,
      "put_iv": 10.8,
      "call_delta": 0.108,
      "put_delta": -0.9375
    },
    {
      "strike": 23750,
      "call_oi": 1784900,
      "put_oi": 68705,
      "call_prev": 2187250,
      "put_prev": 65065,
      "call_ltp": 14.5,
      "put_ltp": 516.15,
      "call_vol": 23901280,
      "put_vol": 155935,
      "call_iv": 13.43,
      "put_iv": 10.96,
      "call_delta": 0.0862,
      "put_delta": -0.9531
    },
    {
      "strike": 23800,
      "call_oi": 5160545,
      "put_oi": 398060,
      "call_prev": 5214495,
      "put_prev": 410865,
      "call_ltp": 11,
      "put_ltp": 564.4,
      "call_vol": 32953830,
      "put_vol": 431730,
      "call_iv": 13.49,
      "put_iv": 11.23,
      "call_delta": 0.068,
      "put_delta": -0.9636
    },
    {
      "strike": 23850,
      "call_oi": 1549210,
      "put_oi": 32500,
      "call_prev": 1300130,
      "put_prev": 29380,
      "call_ltp": 8.6,
      "put_ltp": 603.55,
      "call_vol": 15387385,
      "put_vol": 47840,
      "call_iv": 13.7,
      "put_iv": 0,
      "call_delta": 0.0551,
      "put_delta": -1
    },
    {
      "strike": 23900,
      "call_oi": 3679390,
      "put_oi": 185900,
      "call_prev": 4477850,
      "put_prev": 186550,
      "call_ltp": 6.6,
      "put_ltp": 651.8,
      "call_vol": 27644565,
      "put_vol": 75920,
      "call_iv": 13.82,
      "put_iv": 0,
      "call_delta": 0.0435,
      "put_delta": -1
    },
    {
      "strike": 23950,
      "call_oi": 1245335,
      "put_oi": 21190,
      "call_prev": 1149785,
      "put_prev": 25220,
      "call_ltp": 5.4,
      "put_ltp": 711.65,
      "call_vol": 12010895,
      "put_vol": 14430,
      "call_iv": 14.1,
      "put_iv": 11.35,
      "call_delta": 0.0356,
      "put_delta": -0.9876
    },
    {
      "strike": 24000,
      "call_oi": 8040630,
      "put_oi": 617955,
      "call_prev": 7357285,
      "put_prev": 694525,
      "call_ltp": 4.5,
      "put_ltp": 757.8,
      "call_vol": 41386865,
      "put_vol": 393250,
      "call_iv": 14.4,
      "put_iv": 8.79,
      "call_delta": 0.0295,
      "put_delta": -0.999
    },
    {
      "strike": 24050,
      "call_oi": 1916395,
      "put_oi": 6435,
      "call_prev": 1698970,
      "put_prev": 7345,
      "call_ltp": 3.75,
      "put_ltp": 812.35,
      "call_vol": 11581635,
      "put_vol": 3900,
      "call_iv": 14.77,
      "put_iv": 13.06,
      "call_delta": 0.025,
      "put_delta": -0.9868
    },
    {
      "strike": 24100,
      "call_oi": 3331835,
      "put_oi": 48100,
      "call_prev": 3850145,
      "put_prev": 48360,
      "call_ltp": 3.2,
      "put_ltp": 850.25,
      "call_vol": 20720570,
      "put_vol": 24180,
      "call_iv": 15.14,
      "put_iv": 0,
      "call_delta": 0.0212,
      "put_delta": -1
    },
    {
      "strike": 24150,
      "call_oi": 1061255,
      "put_oi": 2535,
      "call_prev": 1078675,
      "put_prev": 2665,
      "call_ltp": 2.9,
      "put_ltp": 898.15,
      "call_vol": 5854940,
      "put_vol": 1560,
      "call_iv": 15.63,
      "put_iv": 0,
      "call_delta": 0.0189,
      "put_delta": -1
    },
    {
      "strike": 24200,
      "call_oi": 3545425,
      "put_oi": 65390,
      "call_prev": 3221270,
      "put_prev": 65520,
      "call_ltp": 2.55,
      "put_ltp": 945,
      "call_vol": 16107780,
      "put_vol": 22035,
      "call_iv": 15.99,
      "put_iv": 0,
      "call_delta": 0.0162,
      "put_delta": -1
    },
    {
      "strike": 24250,
      "call_oi": 1252225,
      "put_oi": 2535,
      "call_prev": 1229215,
      "put_prev": 2535,
      "call_ltp": 2.4,
      "put_ltp": 1022.9,
      "call_vol": 6420635,
      "put_vol": 0,
      "call_iv": 16.6,
      "put_iv": 22.09,
      "call_delta": 0.0152,
      "put_delta": -0.9474
    },
    {
      "strike": 24300,
      "call_oi": 2793115,
      "put_oi": 33605,
      "call_prev": 2784730,
      "put_prev": 35230,
      "call_ltp": 2.2,
      "put_ltp": 1060.35,
      "call_vol": 18284955,
      "put_vol": 5070,
      "call_iv": 17.09,
      "put_iv": 7.81,
      "call_delta": 0.0137,
      "put_delta": -1
    },
    {
      "strike": 24350,
      "call_oi": 653055,
      "put_oi": 3120,
      "call_prev": 725140,
      "put_prev": 2990,
      "call_ltp": 2.05,
      "put_ltp": 1068,
      "call_vol": 3942705,
      "put_vol": 845,
      "call_iv": 17.58,
      "put_iv": 0,
      "call_delta": 0.0125,
      "put_delta": -1
    },
    {
      "strike": 24400,
      "call_oi": 1993485,
      "put_oi": 31005,
      "call_prev": 3173885,
      "put_prev": 30810,
      "call_ltp": 1.9,
      "put_ltp": 1139.85,
      "call_vol": 11826815,
      "put_vol": 1885,
      "call_iv": 18.07,
      "put_iv": 0,
      "call_delta": 0.0114,
      "put_delta": -1
    },
    {
      "strike": 24450,
      "call_oi": 923260,
      "put_oi": 1690,
      "call_prev": 980785,
      "put_prev": 1690,
      "call_ltp": 1.7,
      "put_ltp": 1174,
      "call_vol": 4011735,
      "put_vol": 455,
      "call_iv": 18.43,
      "put_iv": 0,
      "call_delta": 0.01,
      "put_delta": -1
    },
    {
      "strike": 24500,
      "call_oi": 6872840,
      "put_oi": 181870,
      "call_prev": 6145425,
      "put_prev": 194935,
      "call_ltp": 1.7,
      "put_ltp": 1259.05,
      "call_vol": 17414020,
      "put_vol": 34515,
      "call_iv": 19.04,
      "put_iv": 0,
      "call_delta": 0.0096,
      "put_delta": -1
    },
    {
      "strike": 24550,
      "call_oi": 561405,
      "put_oi": 65,
      "call_prev": 499850,
      "put_prev": 130,
      "call_ltp": 1.45,
      "put_ltp": 1190,
      "call_vol": 1760265,
      "put_vol": 0,
      "call_iv": 19.29,
      "put_iv": 0,
      "call_delta": 0.0082,
      "put_delta": -1
    },
    {
      "strike": 24600,
      "call_oi": 3528330,
      "put_oi": 6500,
      "call_prev": 3599895,
      "put_prev": 6370,
      "call_ltp": 1.4,
      "put_ltp": 1344.65,
      "call_vol": 5127265,
      "put_vol": 0,
      "call_iv": 20.02,
      "put_iv": 0,
      "call_delta": 0.0082,
      "put_delta": -1
    },
    {
      "strike": 24650,
      "call_oi": 428675,
      "put_oi": 1170,
      "call_prev": 431145,
      "put_prev": 1235,
      "call_ltp": 1.25,
      "put_ltp": 1260,
      "call_vol": 1446380,
      "put_vol": 0,
      "call_iv": 20.26,
      "put_iv": 0,
      "call_delta": 0.0071,
      "put_delta": -1
    },
    {
      "strike": 24700,
      "call_oi": 2603510,
      "put_oi": 3445,
      "call_prev": 2387385,
      "put_prev": 3510,
      "call_ltp": 1.15,
      "put_ltp": 1390,
      "call_vol": 5128305,
      "put_vol": 260,
      "call_iv": 20.63,
      "put_iv": 0,
      "call_delta": 0.0063,
      "put_delta": -1
    },
    {
      "strike": 24750,
      "call_oi": 785915,
      "put_oi": 65,
      "call_prev": 792805,
      "put_prev": 65,
      "call_ltp": 1.1,
      "put_ltp": 1296.15,
      "call_vol": 1143220,
      "put_vol": 0,
      "call_iv": 21.24,
      "put_iv": 0,
      "call_delta": 0.0062,
      "put_delta": -1
    },
    {
      "strike": 24800,
      "call_oi": 2173015,
      "put_oi": 47450,
      "call_prev": 1948440,
      "put_prev": 47515,
      "call_ltp": 1,
      "put_ltp": 1489,
      "call_vol": 3953950,
      "put_vol": 260,
      "call_iv": 21.48,
      "put_iv": 0,
      "call_delta": 0.0053,
      "put_delta": -1
    },
    {
      "strike": 24850,
      "call_oi": 423930,
      "put_oi": 130,
      "call_prev": 420550,
      "put_prev": 65,
      "call_ltp": 0.9,
      "put_ltp": 1429.2,
      "call_vol": 1110395,
      "put_vol": 0,
      "call_iv": 21.97,
      "put_iv": 0,
      "call_delta": 0.005,
      "put_delta": -1
    },
    {
      "strike": 24900,
      "call_oi": 2027285,
      "put_oi": 8580,
      "call_prev": 2168270,
      "put_prev": 8645,
      "call_ltp": 0.9,
      "put_ltp": 1600,
      "call_vol": 6063655,
      "put_vol": 325,
      "call_iv": 22.46,
      "put_iv": 0,
      "call_delta": 0.0047,
      "put_delta": -1
    },
    {
      "strike": 24950,
      "call_oi": 316615,
      "put_oi": 65,
      "call_prev": 318435,
      "put_prev": 130,
      "call_ltp": 0.85,
      "put_ltp": 1485.15,
      "call_vol": 761215,
      "put_vol": 0,
      "call_iv": 22.95,
      "put_iv": 0,
      "call_delta": 0.0045,
      "put_delta": -1
    },
    {
      "strike": 25000,
      "call_oi": 4378400,
      "put_oi": 148720,
      "call_prev": 4689490,
      "put_prev": 158470,
      "call_ltp": 0.85,
      "put_ltp": 1752,
      "call_vol": 13235820,
      "put_vol": 14040,
      "call_iv": 23.44,
      "put_iv": 0,
      "call_delta": 0.0043,
      "put_delta": -1
    },
    {
      "strike": 25050,
      "call_oi": 599235,
      "put_oi": 65,
      "call_prev": 620230,
      "put_prev": 585,
      "call_ltp": 0.75,
      "put_ltp": 1889,
      "call_vol": 939835,
      "put_vol": 0,
      "call_iv": 23.68,
      "put_iv": 51.74,
      "call_delta": 0.0038,
      "put_delta": -0.885
    },
    {
      "strike": 25100,
      "call_oi": 1451060,
      "put_oi": 455,
      "call_prev": 1476150,
      "put_prev": 455,
      "call_ltp": 0.7,
      "put_ltp": 1779.25,
      "call_vol": 2904460,
      "put_vol": 0,
      "call_iv": 23.93,
      "put_iv": 0,
      "call_delta": 0.0033,
      "put_delta": -1
    },
    {
      "strike": 25150,
      "call_oi": 300560,
      "put_oi": 130,
      "call_prev": 300950,
      "put_prev": 130,
      "call_ltp": 0.65,
      "put_ltp": 2035,
      "call_vol": 511615,
      "put_vol": 130,
      "call_iv": 24.41,
      "put_iv": 61.83,
      "call_delta": 0.0032,
      "put_delta": -0.8526
    },
    {
      "strike": 25200,
      "call_oi": 1052545,
      "put_oi": 6045,
      "call_prev": 1152190,
      "put_prev": 6045,
      "call_ltp": 0.7,
      "put_ltp": 2095,
      "call_vol": 1442415,
      "put_vol": 325,
      "call_iv": 25.15,
      "put_iv": 64.44,
      "call_delta": 0.0033,
      "put_delta": -0.8481
    },
    {
      "strike": 25250,
      "call_oi": 299585,
      "put_oi": 65,
      "call_prev": 306735,
      "put_prev": 65,
      "call_ltp": 0.6,
      "put_ltp": 1729.8,
      "call_vol": 395590,
      "put_vol": 0,
      "call_iv": 25.39,
      "put_iv": 0,
      "call_delta": 0.0029,
      "put_delta": -1
    },
    {
      "strike": 25300,
      "call_oi": 265915,
      "put_oi": 260,
      "call_prev": 312455,
      "put_prev": 325,
      "call_ltp": 0.65,
      "put_ltp": 2035,
      "call_vol": 726310,
      "put_vol": 0,
      "call_iv": 26.12,
      "put_iv": 0,
      "call_delta": 0.003,
      "put_delta": -1
    },
    {
      "strike": 25350,
      "call_oi": 82290,
      "put_oi": 65,
      "call_prev": 99450,
      "put_prev": 585,
      "call_ltp": 0.65,
      "put_ltp": 2110,
      "call_vol": 158405,
      "put_vol": 0,
      "call_iv": 26.61,
      "put_iv": 0,
      "call_delta": 0.0029,
      "put_delta": -1
    },
    {
      "strike": 25400,
      "call_oi": 130715,
      "put_oi": 2340,
      "call_prev": 186875,
      "put_prev": 2340,
      "call_ltp": 0.7,
      "put_ltp": 1972.7,
      "call_vol": 452465,
      "put_vol": 0,
      "call_iv": 27.34,
      "put_iv": 0,
      "call_delta": 0.0031,
      "put_delta": -1
    },
    {
      "strike": 25450,
      "call_oi": 40690,
      "put_oi": 65,
      "call_prev": 48165,
      "put_prev": 65,
      "call_ltp": 0.65,
      "put_ltp": 2170,
      "call_vol": 68055,
      "put_vol": 65,
      "call_iv": 27.83,
      "put_iv": 0,
      "call_delta": 0.0029,
      "put_delta": -1
    },
    {
      "strike": 25500,
      "call_oi": 1934465,
      "put_oi": 29445,
      "call_prev": 2135315,
      "put_prev": 27755,
      "call_ltp": 0.55,
      "put_ltp": 2260,
      "call_vol": 3779035,
      "put_vol": 3055,
      "call_iv": 27.83,
      "put_iv": 0,
      "call_delta": 0.0025,
      "put_delta": -1
    },
    {
      "strike": 25550,
      "call_oi": 35035,
      "put_oi": 585,
      "call_prev": 30225,
      "put_prev": 520,
      "call_ltp": 0.6,
      "put_ltp": 2314.25,
      "call_vol": 63375,
      "put_vol": 0,
      "call_iv": 28.81,
      "put_iv": 33.69,
      "call_delta": 0.0028,
      "put_delta": -0.9911
    },
    {
      "strike": 25600,
      "call_oi": 183820,
      "put_oi": 1690,
      "call_prev": 236405,
      "put_prev": 1820,
      "call_ltp": 0.55,
      "put_ltp": 2300,
      "call_vol": 414440,
      "put_vol": 195,
      "call_iv": 28.81,
      "put_iv": 0,
      "call_delta": 0.0023,
      "put_delta": -1
    },
    {
      "strike": 25650,
      "call_oi": 21580,
      "put_oi": 65,
      "call_prev": 23205,
      "put_prev": 585,
      "call_ltp": 0.6,
      "put_ltp": 2410,
      "call_vol": 52780,
      "put_vol": 0,
      "call_iv": 29.79,
      "put_iv": 28.81,
      "call_delta": 0.0026,
      "put_delta": -0.9981
    },
    {
      "strike": 25700,
      "call_oi": 146705,
      "put_oi": 65,
      "call_prev": 157365,
      "put_prev": 195,
      "call_ltp": 0.55,
      "put_ltp": 2445,
      "call_vol": 135525,
      "put_vol": 0,
      "call_iv": 29.79,
      "put_iv": 0,
      "call_delta": 0.0022,
      "put_delta": -1
    },
    {
      "strike": 25750,
      "call_oi": 28795,
      "put_oi": 65,
      "call_prev": 34320,
      "put_prev": 65,
      "call_ltp": 0.6,
      "put_ltp": 2212.85,
      "call_vol": 30550,
      "put_vol": 0,
      "call_iv": 30.76,
      "put_iv": 0,
      "call_delta": 0.0025,
      "put_delta": -1
    },
    {
      "strike": 25800,
      "call_oi": 124930,
      "put_oi": 260,
      "call_prev": 123500,
      "put_prev": 260,
      "call_ltp": 0.55,
      "put_ltp": 2650,
      "call_vol": 249600,
      "put_vol": 195,
      "call_iv": 30.76,
      "put_iv": 68.24,
      "call_delta": 0.0021,
      "put_delta": -0.8961
    },
    {
      "strike": 25850,
      "call_oi": 29380,
      "put_oi": 260,
      "call_prev": 28860,
      "put_prev": 260,
      "call_ltp": 0.55,
      "put_ltp": 2620,
      "call_vol": 63310,
      "put_vol": 0,
      "call_iv": 31.25,
      "put_iv": 44.19,
      "call_delta": 0.002,
      "put_delta": -0.9782
    },
    {
      "strike": 25900,
      "call_oi": 152685,
      "put_oi": 130,
      "call_prev": 159575,
      "put_prev": 195,
      "call_ltp": 0.55,
      "put_ltp": 2760,
      "call_vol": 391625,
      "put_vol": 130,
      "call_iv": 32.23,
      "put_iv": 71.84,
      "call_delta": 0.0023,
      "put_delta": -0.8922
    },
    {
      "strike": 25950,
      "call_oi": 26065,
      "put_oi": 65,
      "call_prev": 21645,
      "put_prev": 65,
      "call_ltp": 0.5,
      "put_ltp": 2427.45,
      "call_vol": 40430,
      "put_vol": 0,
      "call_iv": 32.23,
      "put_iv": 0,
      "call_delta": 0.002,
      "put_delta": -1
    },
    {
      "strike": 26000,
      "call_oi": 717080,
      "put_oi": 38415,
      "call_prev": 1056120,
      "put_prev": 38675,
      "call_ltp": 0.5,
      "put_ltp": 2660,
      "call_vol": 1552590,
      "put_vol": 325,
      "call_iv": 32.71,
      "put_iv": 0,
      "call_delta": 0.0019,
      "put_delta": -1
    },
    {
      "strike": 26050,
      "call_oi": 55900,
      "put_oi": 65,
      "call_prev": 58825,
      "put_prev": 65,
      "call_ltp": 0.55,
      "put_ltp": 2528.7,
      "call_vol": 120510,
      "put_vol": 0,
      "call_iv": 33.69,
      "put_iv": 0,
      "call_delta": 0.0022,
      "put_delta": -1
    },
    {
      "strike": 26100,
      "call_oi": 482170,
      "put_oi": 1625,
      "call_prev": 342030,
      "put_prev": 1755,
      "call_ltp": 0.5,
      "put_ltp": 2765,
      "call_vol": 994500,
      "put_vol": 0,
      "call_iv": 33.69,
      "put_iv": 0,
      "call_delta": 0.0018,
      "put_delta": -1
    }
  ]
}